Day6/shift_register.sv
`timescale 1ns / 1ps
//////////////////////////////////////////////////////////////////////////////////
// Company: 
// Engineer: 
// 
// Create Date: 05/04/2024 07:48:01 AM
// Design Name: 
// Module Name: shift_register
// Project Name: 
// Target Devices: 
// Tool Versions: 
// Description: 
// 
// Dependencies: 
// 
// Revision:
// Revision 0.01 - File Created
// Additional Comments:
// 
//////////////////////////////////////////////////////////////////////////////////


module shift_register(
    input wire clk,
    input wire reset,
    input wire x_i, //serial input
    
    output wire [3:0] sr_o
  );
  
  logic [3:0]sr_ff;
  logic [3:0]nxt_sr;
  
  always_ff@(posedge clk or posedge reset)
    if(reset)
        sr_ff <= 4'h0;
    else
        sr_ff <= nxt_sr;
  
  assign nxt_sr = {sr_ff[2:0],x_i};
  assign sr_o = sr_ff;
  
endmodule

Day6/tb_shift_register.sv
`timescale 1ns / 1ps
//////////////////////////////////////////////////////////////////////////////////
// Company: 
// Engineer: 
// 
// Create Date: 05/04/2024 07:48:23 AM
// Design Name: 
// Module Name: tb_shift_register
// Project Name: 
// Target Devices: 
// Tool Versions: 
// Description: 
// 
// Dependencies: 
// 
// Revision:
// Revision 0.01 - File Created
// Additional Comments:
// 
//////////////////////////////////////////////////////////////////////////////////


module tb_shift_register();

logic clk,reset;
logic x_i;
logic [3:0]sr_o;

shift_register day6(.*);

always begin
clk=1'b0;
#5;
clk=1'b1;
#5;

end
initial begin
    reset <= 1'b1;
    x_i <= 1'b0;
    @(posedge clk);
    reset <= 1'b0;
    @(posedge clk);
    for (int i=0; i<16; i=i+1) begin
      x_i <= $random%2;
      @(posedge clk);
    end
    $finish();
  end

  // Dump VCD
  initial begin
    $dumpfile("day6.vcd");
    $dumpvars(2, tb_shift_register);
  end



endmodule

Day6/day6.vcd
$date
   Sat May  4 08:23:07 2024
$end
$version
  2018.2
$end
$timescale
  1ps
$end
$scope module tb_shift_register $end
$var reg 1 ! clk $end
$var reg 1 " reset $end
$var reg 1 # x_i $end
$var reg 4 $ sr_o [3:0] $end
$scope module day6 $end
$var wire 1 % clk $end
$var wire 1 & reset $end
$var wire 1 ' x_i $end
$var wire 4 ( sr_o [3:0] $end
$var reg 4 ) sr_ff [3:0] $end
$var reg 4 * nxt_sr [3:0] $end
$upscope $end
$scope begin Block44_3 $end
$var reg 32 + i $end
$upscope $end
$upscope $end
$enddefinitions $end
#0
$dumpvars
0!
1"
0#
b0 $
0%
1&
0'
b0 (
b0 )
b0 *
b0 +
$end
#5000
1!
0"
1%
0&
b0 )
#10000
0!
0%
#15000
1!
0#
1%
b0 )
b0 +
#20000
0!
0%
#25000
1!
1#
1%
1'
b0 )
b1 *
b1 +
#30000
0!
0%
#35000
1!
1#
b1 $
1%
b1 (
b1 )
b11 *
b10 +
#40000
0!
0%
#45000
1!
1#
b11 $
1%
b11 (
b11 )
b111 *
b11 +
#50000
0!
0%
#55000
1!
1#
b111 $
1%
b111 (
b111 )
b1111 *
b100 +
#60000
0!
0%
#65000
1!
1#
b1111 $
1%
b1111 (
b1111 )
b101 +
#70000
0!
0%
#75000
1!
1#
1%
b1111 )
b110 +
#80000
0!
0%
#85000
1!
0#
1%
0'
b1111 )
b1110 *
b111 +
#90000
0!
0%
#95000
1!
1#
b1110 $
1%
1'
b1110 (
b1110 )
b1101 *
b1000 +
#100000
0!
0%
#105000
1!
1#
b1101 $
1%
b1101 (
b1101 )
b1011 *
b1001 +
#110000
0!
0%
#115000
1!
0#
b1011 $
1%
0'
b1011 (
b1011 )
b110 *
b1010 +
#120000
0!
0%
#125000
1!
1#
b110 $
1%
1'
b110 (
b110 )
b1101 *
b1011 +
#130000
0!
0%
#135000
1!
1#
b1101 $
1%
b1101 (
b1101 )
b1011 *
b1100 +
#140000
0!
0%
#145000
1!
0#
b1011 $
1%
0'
b1011 (
b1011 )
b110 *
b1101 +
#150000
0!
0%
#155000
1!
1#
b110 $
1%
1'
b110 (
b110 )
b1101 *
b1110 +
#160000
0!
0%
#165000
1!
0#
b1101 $
1%
0'
b1101 (
b1101 )
b1010 *
b1111 +
