Day19/para_fifo.sv
`timescale 1ns / 1ps
//////////////////////////////////////////////////////////////////////////////////
// Company: 
// Engineer: 
// 
// Create Date: 06/09/2024 11:37:11 AM
// Design Name: 
// Module Name: para_fifo
// Project Name: 
// Target Devices: 
// Tool Versions: 
// Description: 
// 
// Dependencies: 
// 
// Revision:
// Revision 0.01 - File Created
// Additional Comments:
// 
//////////////////////////////////////////////////////////////////////////////////


module para_fifo #(
    parameter DEPTH = 32,
    parameter DATA_W = 8)
(
    input wire clk,
    input wire reset,
    
    input wire w_en,
    input wire r_en,
    
    input wire [DATA_W-1:0]data_in,
    
    output wire [DATA_W-1:0]data_out,
    output wire empty,
    output wire full
    ); 
      logic [DEPTH-1:0][DATA_W-1:0]fifo_mem;
      
      parameter PTR_W = $clog2(DEPTH);
      logic [PTR_W-1:0]wr_ptr;
      logic [PTR_W-1:0]rd_ptr;
      logic [DATA_W-1:0] fifo_pop_data;
      
      always_ff @(posedge clk or posedge reset)
      begin
        if(reset)begin
            rd_ptr <= {PTR_W+1{1'b0}};
            wr_ptr <= {PTR_W+1{1'b0}};
            fifo_pop_data <={DATA_W+1{1'b0}};
            for(int i=0; i<32; i++) begin
                fifo_mem[i] <= {DATA_W+1{1'b0}};
            end
        end
        else
        begin
            if((w_en == 1'b1) && (full == 1'b0))
            begin
            fifo_mem[wr_ptr]<=data_in;
            wr_ptr <= wr_ptr + 1'b1;
            end
            if((r_en == 1'b1) && (empty == 1'b0))
            begin
            fifo_pop_data <= fifo_mem[rd_ptr];
            rd_ptr <= rd_ptr + 1'b1;
            end
          end
        end  
        
        assign data_out = fifo_pop_data;
        assign empty = ((wr_ptr - rd_ptr) == 0)? 1'b1:1'b0;
        assign full = ((wr_ptr - rd_ptr) == 31)? 1'b1:1'b0;
      
        
 
                             
    
endmodule

Day19/tb_para_fifo.sv
`timescale 1ns / 1ps
//////////////////////////////////////////////////////////////////////////////////
// Company: 
// Engineer: 
// 
// Create Date: 06/09/2024 11:38:16 AM
// Design Name: 
// Module Name: tb_para_fifo
// Project Name: 
// Target Devices: 
// Tool Versions: 
// Description: 
// 
// Dependencies: 
// 
// Revision:
// Revision 0.01 - File Created
// Additional Comments:
// 
//////////////////////////////////////////////////////////////////////////////////


module tb_para_fifo();
 parameter DATA_W = 8;
 parameter DEPTH  = 32;

 logic              clk;
 logic              reset;

 logic              w_en;
 logic[DATA_W-1:0]  data_in;

 logic              r_en;
 logic[DATA_W-1:0]  data_out;

 logic              full;
 logic              empty;

 // Instantiate the RTL
 para_fifo #(.DEPTH(DEPTH), .DATA_W(DATA_W)) Day19(.*);

    always begin
    clk = 1'b0;
    #5;
    clk = 1'b1;
    #5;
    end
    
    initial begin
    reset = 1'b1;
    w_en = 1'b0;
    r_en = 1'b0;
    @(posedge clk);
    reset = 1'b0;
    @(posedge clk);
    @(posedge clk);
    for (int i =0; i<DEPTH; i++)begin
        w_en = 1'b1;
        data_in = $urandom_range(0,2**DATA_W-1);
    @(posedge clk);
    end
    w_en = 1'b0;
    @(posedge clk);
    @(posedge clk);
    for (int i =0; i<DEPTH; i++)begin
    r_en = 1'b1;
    @(posedge clk);
    end
    r_en <= 1'b0;
        @(posedge clk);
        @(posedge clk);
        w_en      <= 1'b1;
        data_in <= $urandom_range(0, 2**DATA_W-1);
        @(posedge clk);
        w_en      <= 1'b0;
        // Push and pop both
        for (int i=0; i<DEPTH; i++) begin
          w_en      <= 1'b1;
          r_en       <= 1'b1;
          data_in <= $urandom_range(0, 2**DATA_W-1);
          @(posedge clk);
        end
        w_en <= 1'b0;
        r_en <= 1'b0;
        @(posedge clk);
        @(posedge clk);
        $finish();
      end
    
      // Dump vcd
      initial begin
        $dumpfile("day19.vcd");
        $dumpvars(0, tb_para_fifo);
      end
    

    

endmodule

Day19/day19.vcd
$date
   Thu Jun 13 09:42:47 2024
$end
$version
  2018.2
$end
$timescale
  1ps
$end
$scope module tb_para_fifo $end
$var reg 1 ! clk $end
$var reg 1 " reset $end
$var reg 1 # w_en $end
$var reg 8 $ data_in [7:0] $end
$var reg 1 % r_en $end
$var reg 8 & data_out [7:0] $end
$var reg 1 ' full $end
$var reg 1 ( empty $end
$var parameter 32 ) DATA_W [31:0] $end
$var parameter 32 * DEPTH [31:0] $end
$scope module Day19 $end
$var wire 1 + clk $end
$var wire 1 , reset $end
$var wire 1 - w_en $end
$var wire 1 . r_en $end
$var wire 8 / data_in [7:0] $end
$var wire 8 0 data_out [7:0] $end
$var wire 1 1 empty $end
$var wire 1 2 full $end
$var reg 256 3 fifo_mem [31:0] $end
$var reg 5 4 wr_ptr [4:0] $end
$var reg 5 5 rd_ptr [4:0] $end
$var reg 8 6 fifo_pop_data [7:0] $end
$var parameter 32 7 DEPTH [31:0] $end
$var parameter 32 8 DATA_W [31:0] $end
$var parameter 32 9 PTR_W [31:0] $end
$scope begin Block52_1 $end
$var reg 32 : i $end
$upscope $end
$upscope $end
$scope begin Block57_4 $end
$var reg 32 ; i $end
$upscope $end
$scope begin Block65_5 $end
$var reg 32 < i $end
$upscope $end
$scope begin Block77_6 $end
$var reg 32 = i $end
$upscope $end
$upscope $end
$enddefinitions $end
#0
$dumpvars
0!
1"
0#
bx $
0%
b0 &
0'
1(
b1000 )
b100000 *
0+
1,
0-
0.
bx /
b0 0
11
02
b0 3
b0 4
b0 5
b0 6
b100000 7
b1000 8
b101 9
b100000 :
b0 ;
b0 <
b0 =
$end
#5000
1!
0"
1+
0,
#10000
0!
0+
#15000
1!
1+
#20000
0!
0+
#25000
1!
1#
b11011011 $
0(
1+
1-
b11011011 /
01
02
b11011011 3
b1 4
#30000
0!
0+
#35000
1!
b10111100 $
1+
b10111100 /
01
02
b1011110011011011 3
b10 4
b1 ;
#40000
0!
0+
#45000
1!
b11111100 $
1+
b11111100 /
01
02
b111111001011110011011011 3
b11 4
b10 ;
#50000
0!
0+
#55000
1!
b10001110 $
1+
b10001110 /
01
02
b10001110111111001011110011011011 3
b100 4
b11 ;
#60000
0!
0+
#65000
1!
b11110000 $
1+
b11110000 /
01
02
b1111000010001110111111001011110011011011 3
b101 4
b100 ;
#70000
0!
0+
#75000
1!
b11011101 $
1+
b11011101 /
01
02
b110111011111000010001110111111001011110011011011 3
b110 4
b101 ;
#80000
0!
0+
#85000
1!
b11110 $
1+
b11110 /
01
02
b11110110111011111000010001110111111001011110011011011 3
b111 4
b110 ;
#90000
0!
0+
#95000
1!
b11001011 $
1+
b11001011 /
01
02
b1100101100011110110111011111000010001110111111001011110011011011 3
b1000 4
b111 ;
#100000
0!
0+
#105000
1!
b10011001 $
1+
b10011001 /
01
02
b100110011100101100011110110111011111000010001110111111001011110011011011 3
b1001 4
b1000 ;
#110000
0!
0+
#115000
1!
b11011 $
1+
b11011 /
01
02
b11011100110011100101100011110110111011111000010001110111111001011110011011011 3
b1010 4
b1001 ;
#120000
0!
0+
#125000
1!
b1011001 $
1+
b1011001 /
01
02
b101100100011011100110011100101100011110110111011111000010001110111111001011110011011011 3
b1011 4
b1010 ;
#130000
0!
0+
#135000
1!
b10001001 $
1+
b10001001 /
01
02
b100010010101100100011011100110011100101100011110110111011111000010001110111111001011110011011011 3
b1100 4
b1011 ;
#140000
0!
0+
#145000
1!
b11111000 $
1+
b11111000 /
01
02
b11111000100010010101100100011011100110011100101100011110110111011111000010001110111111001011110011011011 3
b1101 4
b1100 ;
#150000
0!
0+
#155000
1!
b1111000 $
1+
b1111000 /
01
02
b111100011111000100010010101100100011011100110011100101100011110110111011111000010001110111111001011110011011011 3
b1110 4
b1101 ;
#160000
0!
0+
#165000
1!
b1010100 $
1+
b1010100 /
01
02
b10101000111100011111000100010010101100100011011100110011100101100011110110111011111000010001110111111001011110011011011 3
b1111 4
b1110 ;
#170000
0!
0+
#175000
1!
b10010010 $
1+
b10010010 /
01
02
b10010010010101000111100011111000100010010101100100011011100110011100101100011110110111011111000010001110111111001011110011011011 3
b10000 4
b1111 ;
#180000
0!
0+
#185000
1!
b10010011 $
1+
b10010011 /
01
02
b1001001110010010010101000111100011111000100010010101100100011011100110011100101100011110110111011111000010001110111111001011110011011011 3
b10001 4
b10000 ;
#190000
0!
0+
#195000
1!
b10101110 $
1+
b10101110 /
01
02
b101011101001001110010010010101000111100011111000100010010101100100011011100110011100101100011110110111011111000010001110111111001011110011011011 3
b10010 4
b10001 ;
#200000
0!
0+
#205000
1!
b11011 $
1+
b11011 /
01
02
b11011101011101001001110010010010101000111100011111000100010010101100100011011100110011100101100011110110111011111000010001110111111001011110011011011 3
b10011 4
b10010 ;
#210000
0!
0+
#215000
1!
b10001011 $
1+
b10001011 /
01
02
b1000101100011011101011101001001110010010010101000111100011111000100010010101100100011011100110011100101100011110110111011111000010001110111111001011110011011011 3
b10100 4
b10011 ;
#220000
0!
0+
#225000
1!
b100110 $
1+
b100110 /
01
02
b1001101000101100011011101011101001001110010010010101000111100011111000100010010101100100011011100110011100101100011110110111011111000010001110111111001011110011011011 3
b10101 4
b10100 ;
#230000
0!
0+
#235000
1!
b1110000 $
1+
b1110000 /
01
02
b1110000001001101000101100011011101011101001001110010010010101000111100011111000100010010101100100011011100110011100101100011110110111011111000010001110111111001011110011011011 3
b10110 4
b10101 ;
#240000
0!
0+
#245000
1!
b11101 $
1+
b11101 /
01
02
b1110101110000001001101000101100011011101011101001001110010010010101000111100011111000100010010101100100011011100110011100101100011110110111011111000010001110111111001011110011011011 3
b10111 4
b10110 ;
#250000
0!
0+
#255000
1!
b10111001 $
1+
b10111001 /
01
02
b101110010001110101110000001001101000101100011011101011101001001110010010010101000111100011111000100010010101100100011011100110011100101100011110110111011111000010001110111111001011110011011011 3
b11000 4
b10111 ;
#260000
0!
0+
#265000
1!
b11110 $
1+
b11110 /
01
02
b11110101110010001110101110000001001101000101100011011101011101001001110010010010101000111100011111000100010010101100100011011100110011100101100011110110111011111000010001110111111001011110011011011 3
b11001 4
b11000 ;
#270000
0!
0+
#275000
1!
b111001 $
1+
b111001 /
01
02
b11100100011110101110010001110101110000001001101000101100011011101011101001001110010010010101000111100011111000100010010101100100011011100110011100101100011110110111011111000010001110111111001011110011011011 3
b11010 4
b11001 ;
#280000
0!
0+
#285000
1!
b1000100 $
1+
b1000100 /
01
02
b10001000011100100011110101110010001110101110000001001101000101100011011101011101001001110010010010101000111100011111000100010010101100100011011100110011100101100011110110111011111000010001110111111001011110011011011 3
b11011 4
b11010 ;
#290000
0!
0+
#295000
1!
b1000100 $
1+
01
02
b1000100010001000011100100011110101110010001110101110000001001101000101100011011101011101001001110010010010101000111100011111000100010010101100100011011100110011100101100011110110111011111000010001110111111001011110011011011 3
b11100 4
b11011 ;
#300000
0!
0+
#305000
1!
b10101001 $
1+
b10101001 /
01
02
b1010100101000100010001000011100100011110101110010001110101110000001001101000101100011011101011101001001110010010010101000111100011111000100010010101100100011011100110011100101100011110110111011111000010001110111111001011110011011011 3
b11101 4
b11100 ;
#310000
0!
0+
#315000
1!
b1100010 $
1+
b1100010 /
01
02
b11000101010100101000100010001000011100100011110101110010001110101110000001001101000101100011011101011101001001110010010010101000111100011111000100010010101100100011011100110011100101100011110110111011111000010001110111111001011110011011011 3
b11110 4
b11101 ;
#320000
0!
0+
#325000
1!
b11111101 $
1'
1+
b11111101 /
01
12
b11111101011000101010100101000100010001000011100100011110101110010001110101110000001001101000101100011011101011101001001110010010010101000111100011111000100010010101100100011011100110011100101100011110110111011111000010001110111111001011110011011011 3
b11111 4
b11110 ;
#330000
0!
0+
#335000
1!
b11000111 $
1+
b11000111 /
b11111 ;
#340000
0!
0+
#345000
1!
0#
1+
0-
b100000 ;
#350000
0!
0+
#355000
1!
1+
#360000
0!
0+
#365000
1!
1%
b11011011 &
0'
1+
1.
b11011011 0
01
02
b1 5
b11011011 6
#370000
0!
0+
#375000
1!
b10111100 &
1+
b10111100 0
01
02
b10 5
b10111100 6
b1 <
#380000
0!
0+
#385000
1!
b11111100 &
1+
b11111100 0
01
02
b11 5
b11111100 6
b10 <
#390000
0!
0+
#395000
1!
b10001110 &
1+
b10001110 0
01
02
b100 5
b10001110 6
b11 <
#400000
0!
0+
#405000
1!
b11110000 &
1+
b11110000 0
01
02
b101 5
b11110000 6
b100 <
#410000
0!
0+
#415000
1!
b11011101 &
1+
b11011101 0
01
02
b110 5
b11011101 6
b101 <
#420000
0!
0+
#425000
1!
b11110 &
1+
b11110 0
01
02
b111 5
b11110 6
b110 <
#430000
0!
0+
#435000
1!
b11001011 &
1+
b11001011 0
01
02
b1000 5
b11001011 6
b111 <
#440000
0!
0+
#445000
1!
b10011001 &
1+
b10011001 0
01
02
b1001 5
b10011001 6
b1000 <
#450000
0!
0+
#455000
1!
b11011 &
1+
b11011 0
01
02
b1010 5
b11011 6
b1001 <
#460000
0!
0+
#465000
1!
b1011001 &
1+
b1011001 0
01
02
b1011 5
b1011001 6
b1010 <
#470000
0!
0+
#475000
1!
b10001001 &
1+
b10001001 0
01
02
b1100 5
b10001001 6
b1011 <
#480000
0!
0+
#485000
1!
b11111000 &
1+
b11111000 0
01
02
b1101 5
b11111000 6
b1100 <
#490000
0!
0+
#495000
1!
b1111000 &
1+
b1111000 0
01
02
b1110 5
b1111000 6
b1101 <
#500000
0!
0+
#505000
1!
b1010100 &
1+
b1010100 0
01
02
b1111 5
b1010100 6
b1110 <
#510000
0!
0+
#515000
1!
b10010010 &
1+
b10010010 0
01
02
b10000 5
b10010010 6
b1111 <
#520000
0!
0+
#525000
1!
b10010011 &
1+
b10010011 0
01
02
b10001 5
b10010011 6
b10000 <
#530000
0!
0+
#535000
1!
b10101110 &
1+
b10101110 0
01
02
b10010 5
b10101110 6
b10001 <
#540000
0!
0+
#545000
1!
b11011 &
1+
b11011 0
01
02
b10011 5
b11011 6
b10010 <
#550000
0!
0+
#555000
1!
b10001011 &
1+
b10001011 0
01
02
b10100 5
b10001011 6
b10011 <
#560000
0!
0+
#565000
1!
b100110 &
1+
b100110 0
01
02
b10101 5
b100110 6
b10100 <
#570000
0!
0+
#575000
1!
b1110000 &
1+
b1110000 0
01
02
b10110 5
b1110000 6
b10101 <
#580000
0!
0+
#585000
1!
b11101 &
1+
b11101 0
01
02
b10111 5
b11101 6
b10110 <
#590000
0!
0+
#595000
1!
b10111001 &
1+
b10111001 0
01
02
b11000 5
b10111001 6
b10111 <
#600000
0!
0+
#605000
1!
b11110 &
1+
b11110 0
01
02
b11001 5
b11110 6
b11000 <
#610000
0!
0+
#615000
1!
b111001 &
1+
b111001 0
01
02
b11010 5
b111001 6
b11001 <
#620000
0!
0+
#625000
1!
b1000100 &
1+
b1000100 0
01
02
b11011 5
b1000100 6
b11010 <
#630000
0!
0+
#635000
1!
1+
01
02
b11100 5
b11011 <
#640000
0!
0+
#645000
1!
b10101001 &
1+
b10101001 0
01
02
b11101 5
b10101001 6
b11100 <
#650000
0!
0+
#655000
1!
b1100010 &
1+
b1100010 0
01
02
b11110 5
b1100010 6
b11101 <
#660000
0!
0+
#665000
1!
b11111101 &
1(
1+
b11111101 0
11
02
b11111 5
b11111101 6
b11110 <
#670000
0!
0+
#675000
1!
1+
b11111 <
#680000
0!
0+
#685000
1!
0%
1+
0.
b100000 <
#690000
0!
0+
#695000
1!
1+
#700000
0!
0+
#705000
1!
1#
b10011011 $
1+
1-
b10011011 /
#710000
0!
0+
#715000
1!
1#
b1000001 $
1%
0(
1+
1.
b1000001 /
01
02
b1001101111111101011000101010100101000100010001000011100100011110101110010001110101110000001001101000101100011011101011101001001110010010010101000111100011111000100010010101100100011011100110011100101100011110110111011111000010001110111111001011110011011011 3
b0 4
#720000
0!
0+
#725000
1!
b1011 $
b10011011 &
1+
b1011 /
b10011011 0
01
02
b1001101111111101011000101010100101000100010001000011100100011110101110010001110101110000001001101000101100011011101011101001001110010010010101000111100011111000100010010101100100011011100110011100101100011110110111011111000010001110111111001011110001000001 3
b1 4
b0 5
b10011011 6
b1 =
#730000
0!
0+
#735000
1!
b1000100 $
b1000001 &
1+
b1000100 /
b1000001 0
01
02
b1001101111111101011000101010100101000100010001000011100100011110101110010001110101110000001001101000101100011011101011101001001110010010010101000111100011111000100010010101100100011011100110011100101100011110110111011111000010001110111111000000101101000001 3
b10 4
b1 5
b1000001 6
b10 =
#740000
0!
0+
#745000
1!
b10100011 $
b1011 &
1+
b10100011 /
b1011 0
01
02
b1001101111111101011000101010100101000100010001000011100100011110101110010001110101110000001001101000101100011011101011101001001110010010010101000111100011111000100010010101100100011011100110011100101100011110110111011111000010001110010001000000101101000001 3
b11 4
b10 5
b1011 6
b11 =
#750000
0!
0+
#755000
1!
b1000 $
b1000100 &
1+
b1000 /
b1000100 0
01
02
b1001101111111101011000101010100101000100010001000011100100011110101110010001110101110000001001101000101100011011101011101001001110010010010101000111100011111000100010010101100100011011100110011100101100011110110111011111000010100011010001000000101101000001 3
b100 4
b11 5
b1000100 6
b100 =
#760000
0!
0+
#765000
1!
b1011 $
b10100011 &
1+
b1011 /
b10100011 0
01
02
b1001101111111101011000101010100101000100010001000011100100011110101110010001110101110000001001101000101100011011101011101001001110010010010101000111100011111000100010010101100100011011100110011100101100011110110111010000100010100011010001000000101101000001 3
b101 4
b100 5
b10100011 6
b101 =
#770000
0!
0+
#775000
1!
b111110 $
b1000 &
1+
b111110 /
b1000 0
01
02
b1001101111111101011000101010100101000100010001000011100100011110101110010001110101110000001001101000101100011011101011101001001110010010010101000111100011111000100010010101100100011011100110011100101100011110000010110000100010100011010001000000101101000001 3
b110 4
b101 5
b1000 6
b110 =
#780000
0!
0+
#785000
1!
b1001001 $
b1011 &
1+
b1001001 /
b1011 0
01
02
b1001101111111101011000101010100101000100010001000011100100011110101110010001110101110000001001101000101100011011101011101001001110010010010101000111100011111000100010010101100100011011100110011100101100111110000010110000100010100011010001000000101101000001 3
b111 4
b110 5
b1011 6
b111 =
#790000
0!
0+
#795000
1!
b10110 $
b111110 &
1+
b10110 /
b111110 0
01
02
b1001101111111101011000101010100101000100010001000011100100011110101110010001110101110000001001101000101100011011101011101001001110010010010101000111100011111000100010010101100100011011100110010100100100111110000010110000100010100011010001000000101101000001 3
b1000 4
b111 5
b111110 6
b1000 =
#800000
0!
0+
#805000
1!
b10000010 $
b1001001 &
1+
b10000010 /
b1001001 0
01
02
b1001101111111101011000101010100101000100010001000011100100011110101110010001110101110000001001101000101100011011101011101001001110010010010101000111100011111000100010010101100100011011000101100100100100111110000010110000100010100011010001000000101101000001 3
b1001 4
b1000 5
b1001001 6
b1001 =
#810000
0!
0+
#815000
1!
b11101101 $
b10110 &
1+
b11101101 /
b10110 0
01
02
b1001101111111101011000101010100101000100010001000011100100011110101110010001110101110000001001101000101100011011101011101001001110010010010101000111100011111000100010010101100110000010000101100100100100111110000010110000100010100011010001000000101101000001 3
b1010 4
b1001 5
b10110 6
b1010 =
#820000
0!
0+
#825000
1!
b11110 $
b10000010 &
1+
b11110 /
b10000010 0
01
02
b1001101111111101011000101010100101000100010001000011100100011110101110010001110101110000001001101000101100011011101011101001001110010010010101000111100011111000100010011110110110000010000101100100100100111110000010110000100010100011010001000000101101000001 3
b1011 4
b1010 5
b10000010 6
b1011 =
#830000
0!
0+
#835000
1!
b10001101 $
b11101101 &
1+
b10001101 /
b11101101 0
01
02
b1001101111111101011000101010100101000100010001000011100100011110101110010001110101110000001001101000101100011011101011101001001110010010010101000111100011111000000111101110110110000010000101100100100100111110000010110000100010100011010001000000101101000001 3
b1100 4
b1011 5
b11101101 6
b1100 =
#840000
0!
0+
#845000
1!
b101011 $
b11110 &
1+
b101011 /
b11110 0
01
02
b1001101111111101011000101010100101000100010001000011100100011110101110010001110101110000001001101000101100011011101011101001001110010010010101000111100010001101000111101110110110000010000101100100100100111110000010110000100010100011010001000000101101000001 3
b1101 4
b1100 5
b11110 6
b1101 =
#850000
0!
0+
#855000
1!
b1100111 $
b10001101 &
1+
b1100111 /
b10001101 0
01
02
b1001101111111101011000101010100101000100010001000011100100011110101110010001110101110000001001101000101100011011101011101001001110010010010101000010101110001101000111101110110110000010000101100100100100111110000010110000100010100011010001000000101101000001 3
b1110 4
b1101 5
b10001101 6
b1110 =
#860000
0!
0+
#865000
1!
b10100011 $
b101011 &
1+
b10100011 /
b101011 0
01
02
b1001101111111101011000101010100101000100010001000011100100011110101110010001110101110000001001101000101100011011101011101001001110010010011001110010101110001101000111101110110110000010000101100100100100111110000010110000100010100011010001000000101101000001 3
b1111 4
b1110 5
b101011 6
b1111 =
#870000
0!
0+
#875000
1!
b10101110 $
b1100111 &
1+
b10101110 /
b1100111 0
01
02
b1001101111111101011000101010100101000100010001000011100100011110101110010001110101110000001001101000101100011011101011101001001110100011011001110010101110001101000111101110110110000010000101100100100100111110000010110000100010100011010001000000101101000001 3
b10000 4
b1111 5
b1100111 6
b10000 =
#880000
0!
0+
#885000
1!
b1010100 $
b10100011 &
1+
b1010100 /
b10100011 0
01
02
b1001101111111101011000101010100101000100010001000011100100011110101110010001110101110000001001101000101100011011101011101010111010100011011001110010101110001101000111101110110110000010000101100100100100111110000010110000100010100011010001000000101101000001 3
b10001 4
b10000 5
b10100011 6
b10001 =
#890000
0!
0+
#895000
1!
b11000001 $
b10101110 &
1+
b11000001 /
b10101110 0
01
02
b1001101111111101011000101010100101000100010001000011100100011110101110010001110101110000001001101000101100011011010101001010111010100011011001110010101110001101000111101110110110000010000101100100100100111110000010110000100010100011010001000000101101000001 3
b10010 4
b10001 5
b10101110 6
b10010 =
#900000
0!
0+
#905000
1!
b111011 $
b1010100 &
1+
b111011 /
b1010100 0
01
02
b1001101111111101011000101010100101000100010001000011100100011110101110010001110101110000001001101000101111000001010101001010111010100011011001110010101110001101000111101110110110000010000101100100100100111110000010110000100010100011010001000000101101000001 3
b10011 4
b10010 5
b1010100 6
b10011 =
#910000
0!
0+
#915000
1!
b10000000 $
b11000001 &
1+
b10000000 /
b11000001 0
01
02
b1001101111111101011000101010100101000100010001000011100100011110101110010001110101110000001001100011101111000001010101001010111010100011011001110010101110001101000111101110110110000010000101100100100100111110000010110000100010100011010001000000101101000001 3
b10100 4
b10011 5
b11000001 6
b10100 =
#920000
0!
0+
#925000
1!
b101001 $
b111011 &
1+
b101001 /
b111011 0
01
02
b1001101111111101011000101010100101000100010001000011100100011110101110010001110101110000100000000011101111000001010101001010111010100011011001110010101110001101000111101110110110000010000101100100100100111110000010110000100010100011010001000000101101000001 3
b10101 4
b10100 5
b111011 6
b10101 =
#930000
0!
0+
#935000
1!
b11011111 $
b10000000 &
1+
b11011111 /
b10000000 0
01
02
b1001101111111101011000101010100101000100010001000011100100011110101110010001110100101001100000000011101111000001010101001010111010100011011001110010101110001101000111101110110110000010000101100100100100111110000010110000100010100011010001000000101101000001 3
b10110 4
b10101 5
b10000000 6
b10110 =
#940000
0!
0+
#945000
1!
b101110 $
b101001 &
1+
b101110 /
b101001 0
01
02
b1001101111111101011000101010100101000100010001000011100100011110101110011101111100101001100000000011101111000001010101001010111010100011011001110010101110001101000111101110110110000010000101100100100100111110000010110000100010100011010001000000101101000001 3
b10111 4
b10110 5
b101001 6
b10111 =
#950000
0!
0+
#955000
1!
b1111101 $
b11011111 &
1+
b1111101 /
b11011111 0
01
02
b1001101111111101011000101010100101000100010001000011100100011110001011101101111100101001100000000011101111000001010101001010111010100011011001110010101110001101000111101110110110000010000101100100100100111110000010110000100010100011010001000000101101000001 3
b11000 4
b10111 5
b11011111 6
b11000 =
#960000
0!
0+
#965000
1!
b10100000 $
b101110 &
1+
b10100000 /
b101110 0
01
02
b1001101111111101011000101010100101000100010001000011100101111101001011101101111100101001100000000011101111000001010101001010111010100011011001110010101110001101000111101110110110000010000101100100100100111110000010110000100010100011010001000000101101000001 3
b11001 4
b11000 5
b101110 6
b11001 =
#970000
0!
0+
#975000
1!
b1101001 $
b1111101 &
1+
b1101001 /
b1111101 0
01
02
b1001101111111101011000101010100101000100010001001010000001111101001011101101111100101001100000000011101111000001010101001010111010100011011001110010101110001101000111101110110110000010000101100100100100111110000010110000100010100011010001000000101101000001 3
b11010 4
b11001 5
b1111101 6
b11010 =
#980000
0!
0+
#985000
1!
b11111101 $
b10100000 &
1+
b11111101 /
b10100000 0
01
02
b1001101111111101011000101010100101000100011010011010000001111101001011101101111100101001100000000011101111000001010101001010111010100011011001110010101110001101000111101110110110000010000101100100100100111110000010110000100010100011010001000000101101000001 3
b11011 4
b11010 5
b10100000 6
b11011 =
#990000
0!
0+
#995000
1!
b11001001 $
b1101001 &
1+
b11001001 /
b1101001 0
01
02
b1001101111111101011000101010100111111101011010011010000001111101001011101101111100101001100000000011101111000001010101001010111010100011011001110010101110001101000111101110110110000010000101100100100100111110000010110000100010100011010001000000101101000001 3
b11100 4
b11011 5
b1101001 6
b11100 =
