Day4/ALU.sv
`timescale 1ns / 1ps
//////////////////////////////////////////////////////////////////////////////////
// Company: 
// Engineer: 
// 
// Create Date: 05/04/2024 06:21:04 AM
// Design Name: 
// Module Name: ALU
// Project Name: 
// Target Devices: 
// Tool Versions: 
// Description: 
// 
// Dependencies: 
// 
// Revision:
// Revision 0.01 - File Created
// Additional Comments:
// 
//////////////////////////////////////////////////////////////////////////////////


module ALU(
input logic [7:0] a_i,
input logic [7:0] b_i,

input logic [2:0]op_i,

output logic [7:0] alu_o
    );
    
     localparam  OP_ADD = 3'b000;
     localparam  OP_SUB = 3'b001;
     localparam  OP_SLL = 3'b010; //Shift logic left
     localparam  OP_LSR = 3'b011; //logic shift right
     localparam  OP_AND = 3'b100;
     localparam  OP_OR  = 3'b101;
     localparam  OP_XOR = 3'b110;
     localparam  OP_EQL = 3'b111;
     
    logic carry;
    
    always_comb begin
        case(op_i)
        OP_ADD: {carry,alu_o} = {1'b0,a_i} + {1'b0,b_i};
        OP_SUB: alu_o = a_i - b_i;
        OP_SLL: alu_o = a_i[7:0] << b_i[2:0];
         OP_LSR: alu_o = a_i[7:0] >> b_i[2:0];
             OP_AND: alu_o = a_i[7:0] & b_i[7:0];
             OP_OR:  alu_o = a_i | b_i;
             OP_XOR: alu_o = a_i ^ b_i;
             OP_EQL: alu_o = {7'h0, a_i == b_i};
        endcase
    
    end
endmodule

Day4/tb_ALU.sv
`timescale 1ns / 1ps
//////////////////////////////////////////////////////////////////////////////////
// Company: 
// Engineer: 
// 
// Create Date: 05/04/2024 06:48:50 AM
// Design Name: 
// Module Name: tb_ALU
// Project Name: 
// Target Devices: 
// Tool Versions: 
// Description: 
// 
// Dependencies: 
// 
// Revision:
// Revision 0.01 - File Created
// Additional Comments:
// 
//////////////////////////////////////////////////////////////////////////////////


module tb_ALU();

logic [7:0] a_i,b_i;
logic [2:0]op_i;
logic [7:0]alu_o;

ALU day4(.*);

initial begin
    for(int j=0; j<3; j++) begin
        for(int i=0; i<7; i++)begin
        a_i = $urandom_range(0,8'hff);
        b_i = $urandom_range(0,8'hff);
        op_i = 3'(i);
        #5;
        end
      end
end
initial begin
$dumpfile("day4.vcd");
$dumpvars(0,tb_ALU);
end
endmodule

Day4/day4.vcd
$date
   Sat May  4 09:34:03 2024
$end
$version
  2018.2
$end
$timescale
  1ps
$end
$scope module tb_ALU $end
$var reg 8 ! a_i [7:0] $end
$var reg 8 " b_i [7:0] $end
$var reg 3 # op_i [2:0] $end
$var reg 8 $ alu_o [7:0] $end
$scope module day4 $end
$var wire 8 % a_i [7:0] $end
$var wire 8 & b_i [7:0] $end
$var wire 3 ' op_i [2:0] $end
$var reg 8 $ alu_o [7:0] $end
$var reg 1 ( carry $end
$var parameter 3 ) OP_ADD [2:0] $end
$var parameter 3 * OP_SUB [2:0] $end
$var parameter 3 + OP_SLL [2:0] $end
$var parameter 3 , OP_LSR [2:0] $end
$var parameter 3 - OP_AND [2:0] $end
$var parameter 3 . OP_OR [2:0] $end
$var parameter 3 / OP_XOR [2:0] $end
$var parameter 3 0 OP_EQL [2:0] $end
$upscope $end
$scope begin Block32_2 $end
$var reg 32 1 j $end
$scope begin Block33_3 $end
$var reg 32 2 i $end
$upscope $end
$upscope $end
$upscope $end
$enddefinitions $end
#0
$dumpvars
b10110010 !
b10100001 "
b0 #
b1010011 $
b10110010 %
b10100001 &
b0 '
1(
b0 )
b1 *
b10 +
b11 ,
b100 -
b101 .
b110 /
b111 0
b0 1
b0 2
$end
#5000
b1011010 !
b1011101 "
b1 #
b11111101 $
b1011010 %
b1011101 &
b1 '
b1 2
#10000
b10101110 !
b11111011 "
b10 #
b1110000 $
b10101110 %
b11111011 &
b10 '
b10 2
#15000
b100101 !
b1100000 "
b11 #
b100101 $
b100101 %
b1100000 &
b11 '
b11 2
#20000
b10011100 !
b1111111 "
b100 #
b11100 $
b10011100 %
b1111111 &
b100 '
b100 2
#25000
b10111101 !
b1001010 "
b101 #
b11111111 $
b10111101 %
b1001010 &
b101 '
b101 2
#30000
b1111010 !
b11100011 "
b110 #
b10011001 $
b1111010 %
b11100011 &
b110 '
b110 2
#35000
b10101011 !
b10111 "
b0 #
b11000010 $
b10101011 %
b10111 &
b0 '
0(
b1 1
b0 2
#40000
b1100010 !
b1101000 "
b1 #
b11111010 $
b1100010 %
b1101000 &
b1 '
b1 2
#45000
b1100001 !
b11011101 "
b10 #
b100000 $
b1100001 %
b11011101 &
b10 '
b10 2
#50000
b1001011 !
b1100 "
b11 #
b100 $
b1001011 %
b1100 &
b11 '
b11 2
#55000
b11110100 !
b10101110 "
b100 #
b10100100 $
b11110100 %
b10101110 &
b100 '
b100 2
#60000
b1110101 !
b1010101 "
b101 #
b1110101 $
b1110101 %
b1010101 &
b101 '
b101 2
#65000
b10001011 !
b11000000 "
b110 #
b1001011 $
b10001011 %
b11000000 &
b110 '
b110 2
#70000
b1100010 !
b1111111 "
b0 #
b11100001 $
b1100010 %
b1111111 &
b0 '
b10 1
b0 2
#75000
b1101110 !
b11010111 "
b1 #
b10010111 $
b1101110 %
b11010111 &
b1 '
b1 2
#80000
b11010100 !
b11111001 "
b10 #
b10101000 $
b11010100 %
b11111001 &
b10 '
b10 2
#85000
b10010111 !
b110110 "
b11 #
b10 $
b10010111 %
b110110 &
b11 '
b11 2
#90000
b1111000 !
b110 "
b100 #
b0 $
b1111000 %
b110 &
b100 '
b100 2
#95000
b1101 !
b1001101 "
b101 #
b1001101 $
b1101 %
b1001101 &
b101 '
b101 2
#100000
b11111111 !
b10100101 "
b110 #
b1011010 $
b11111111 %
b10100101 &
b110 '
b110 2
#105000
b11 1
b111 2
