Day3/edge_detector.sv
`timescale 1ns / 1ps
//////////////////////////////////////////////////////////////////////////////////
// Company: 
// Engineer: 
// 
// Create Date: 05/04/2024 05:54:02 AM
// Design Name: 
// Module Name: edge_detector
// Project Name: 
// Target Devices: 
// Tool Versions: 
// Description: 
// 
// Dependencies: 
// 
// Revision:
// Revision 0.01 - File Created
// Additional Comments:
// 
//////////////////////////////////////////////////////////////////////////////////


module edge_detector(
input wire clk,
input wire reset,

input wire a_i,

output wire rising_edge_o,
output wire falling_edge_o
    );
    
    logic a_ff;
    
    always @(posedge clk or posedge reset)
    if(reset)
    a_ff <= 1'b0;
    else
    a_ff <= a_i;
    
    assign rising_edge_o = ~a_ff & a_i;
    assign falling_edge_o = a_ff & ~a_i;
    
endmodule

Day3/tb_edge.sv
// Simple edge detector TB

module tb_edge ();

  logic    clk;
  logic    reset;

  logic    a_i;

  logic    rising_edge_o;
  logic    falling_edge_o;

  edge_detector day3 (.*);

  // clk
  always begin
    clk = 1'b1;
    #5;
    clk = 1'b0;
    #5;
  end

  // Stimulus
  initial begin
    reset <= 1'b1;
    a_i <= 1'b1;
    @(posedge clk);
    reset <= 1'b0;
    @(posedge clk);
    for (int i=0; i<32; i++) begin
      a_i <= $random%2;
      @(posedge clk);
    end
    $finish();
  end

  // Dump VCD
  initial begin
    $dumpfile("day3.vcd");
    $dumpvars(0, tb_edge);
  end

endmodule

Day3/day3.vcd
$date
   Sat May  4 06:13:16 2024
$end
$version
  2018.2
$end
$timescale
  1ps
$end
$scope module tb_edge $end
$var reg 1 ! clk $end
$var reg 1 " reset $end
$var reg 1 # a_i $end
$var reg 1 $ rising_edge_o $end
$var reg 1 % falling_edge_o $end
$scope module day3 $end
$var wire 1 & clk $end
$var wire 1 ' reset $end
$var wire 1 ( a_i $end
$var wire 1 ) rising_edge_o $end
$var wire 1 * falling_edge_o $end
$var reg 1 + a_ff $end
$upscope $end
$scope begin Block30_3 $end
$var reg 32 , i $end
$upscope $end
$upscope $end
$enddefinitions $end
#0
$dumpvars
1!
1"
1#
1$
0%
1&
1'
1(
1)
0*
0+
b0 ,
$end
#5000
0!
0&
#10000
1!
0"
1&
0'
#15000
0!
0&
#20000
1!
0#
0$
1%
1&
0(
0)
1*
1+
#25000
0!
0&
#30000
1!
1#
1$
0%
1&
1(
1)
0*
0+
b1 ,
#35000
0!
0&
#40000
1!
0$
1&
0)
0*
1+
b10 ,
#45000
0!
0&
#50000
1!
1&
b11 ,
#55000
0!
0&
#60000
1!
1&
b100 ,
#65000
0!
0&
#70000
1!
1&
b101 ,
#75000
0!
0&
#80000
1!
1&
b110 ,
#85000
0!
0&
#90000
1!
0#
1%
1&
0(
0)
1*
b111 ,
#95000
0!
0&
#100000
1!
1#
1$
0%
1&
1(
1)
0*
0+
b1000 ,
#105000
0!
0&
#110000
1!
0$
1&
0)
0*
1+
b1001 ,
#115000
0!
0&
#120000
1!
0#
1%
1&
0(
0)
1*
b1010 ,
#125000
0!
0&
#130000
1!
1#
1$
0%
1&
1(
1)
0*
0+
b1011 ,
#135000
0!
0&
#140000
1!
0$
1&
0)
0*
1+
b1100 ,
#145000
0!
0&
#150000
1!
0#
1%
1&
0(
0)
1*
b1101 ,
#155000
0!
0&
#160000
1!
1#
1$
0%
1&
1(
1)
0*
0+
b1110 ,
#165000
0!
0&
#170000
1!
0#
0$
1%
1&
0(
0)
1*
1+
b1111 ,
#175000
0!
0&
#180000
1!
1#
1$
0%
1&
1(
1)
0*
0+
b10000 ,
#185000
0!
0&
#190000
1!
0#
0$
1%
1&
0(
0)
1*
1+
b10001 ,
#195000
0!
0&
#200000
1!
1#
1$
0%
1&
1(
1)
0*
0+
b10010 ,
#205000
0!
0&
#210000
1!
0$
1&
0)
0*
1+
b10011 ,
#215000
0!
0&
#220000
1!
0#
1%
1&
0(
0)
1*
b10100 ,
#225000
0!
0&
#230000
1!
1#
1$
0%
1&
1(
1)
0*
0+
b10101 ,
#235000
0!
0&
#240000
1!
0#
0$
1%
1&
0(
0)
1*
1+
b10110 ,
#245000
0!
0&
#250000
1!
0%
1&
0)
0*
0+
b10111 ,
#255000
0!
0&
#260000
1!
1&
b11000 ,
#265000
0!
0&
#270000
1!
1#
1$
1&
1(
1)
0*
b11001 ,
#275000
0!
0&
#280000
1!
0#
0$
1%
1&
0(
0)
1*
1+
b11010 ,
#285000
0!
0&
#290000
1!
1#
1$
0%
1&
1(
1)
0*
0+
b11011 ,
#295000
0!
0&
#300000
1!
0$
1&
0)
0*
1+
b11100 ,
#305000
0!
0&
#310000
1!
1&
b11101 ,
#315000
0!
0&
#320000
1!
1&
b11110 ,
#325000
0!
0&
#330000
1!
0#
1%
1&
0(
0)
1*
b11111 ,
