Day14/priority_arbiter.sv
`timescale 1ns / 1ps
//////////////////////////////////////////////////////////////////////////////////
// Company: 
// Engineer: 
// 
// Create Date: 05/07/2024 06:30:14 AM
// Design Name: 
// Module Name: priority_arbiter
// Project Name: 
// Target Devices: 
// Tool Versions: 
// Description: 
// 
// Dependencies: 
// 
// Revision:
// Revision 0.01 - File Created
// Additional Comments:
// 
//////////////////////////////////////////////////////////////////////////////////


module priority_arbiter #(
    parameter NUM_PORTS = 4
)(
    input wire [NUM_PORTS-1:0]req_i,
    output wire [NUM_PORTS-1:0]gnt_o
    );
    
    assign gnt_o[0] = req_i[0];
    
    genvar i;
    for (i=1; i<NUM_PORTS; i=i+1) begin
        assign gnt_o[i] = req_i[i] & (|gnt_o[i-1:0]);
    end
    
    
endmodule

Day14/tb_priority_arbiter.sv
`timescale 1ns / 1ps
//////////////////////////////////////////////////////////////////////////////////
// Company: 
// Engineer: 
// 
// Create Date: 05/07/2024 06:30:47 AM
// Design Name: 
// Module Name: tb_priority_arbiter
// Project Name: 
// Target Devices: 
// Tool Versions: 
// Description: 
// 
// Dependencies: 
// 
// Revision:
// Revision 0.01 - File Created
// Additional Comments:
// 
//////////////////////////////////////////////////////////////////////////////////


module tb_priority_arbiter();

    localparam NUM_PORTS = 8;
    
    logic [NUM_PORTS-1:0] req_i;
    logic [NUM_PORTS-1:0] gnt_o;
    
    priority_arbiter #(NUM_PORTS) day14(.*);

 initial begin
    for (int i=0; i<32; i=i+1) begin
      req_i = $urandom_range(0, 2**NUM_PORTS-1);
      #5;
    end
  end

  initial begin
    $dumpfile("day14.vcd");
    $dumpvars(0, tb_priority_arbiter);
  end


endmodule

Day14/day14.vcd
$date
   Thu May  9 21:50:51 2024
$end
$version
  2018.2
$end
$timescale
  1ps
$end
$scope module tb_priority_arbiter $end
$var reg 8 ! req_i [7:0] $end
$var reg 8 " gnt_o [7:0] $end
$var parameter 32 # NUM_PORTS [31:0] $end
$scope module day14 $end
$var wire 8 $ req_i [7:0] $end
$var wire 8 % gnt_o [7:0] $end
$var parameter 32 & NUM_PORTS [31:0] $end
$upscope $end
$scope begin Block33_1 $end
$var reg 32 ' i $end
$upscope $end
$upscope $end
$enddefinitions $end
#0
$dumpvars
b11100011 !
b11100011 "
b1000 #
b11100011 $
b11100011 %
b1000 &
b0 '
$end
#5000
b1011 !
b1011 "
b1011 $
b1011 %
b1 '
#10000
b11010100 !
b0 "
b11010100 $
b0 %
b10 '
#15000
b11110110 !
b11110110 $
b0 %
b11 '
#20000
b11000101 !
b11000101 "
b11000101 $
b11000101 %
b100 '
#25000
b11000001 !
b11000001 "
b11000001 $
b11000001 %
b101 '
#30000
b1000011 !
b1000011 "
b1000011 $
b1000011 %
b110 '
#35000
b10101000 !
b0 "
b10101000 $
b0 %
b111 '
#40000
b11001101 !
b11001101 "
b11001101 $
b11001101 %
b1000 '
#45000
b10111 !
b10111 "
b10111 $
b10111 %
b1001 '
#50000
b10011111 !
b10011111 "
b10011111 $
b10011111 %
b1010 '
#55000
b10010010 !
b0 "
b10010010 $
b0 %
b1011 '
#60000
b11011000 !
b11011000 $
b0 %
b1100 '
#65000
b11100010 !
b11100010 $
b0 %
b1101 '
#70000
b111010 !
b111010 $
b0 %
b1110 '
#75000
b10100101 !
b10100101 "
b10100101 $
b10100101 %
b1111 '
#80000
b11111001 !
b11111001 "
b11111001 $
b11111001 %
b10000 '
#85000
b11011001 !
b11011001 "
b11011001 $
b11011001 %
b10001 '
#90000
b110111 !
b110111 "
b110111 $
b110111 %
b10010 '
#95000
b11010001 !
b11010001 "
b11010001 $
b11010001 %
b10011 '
#100000
b10111011 !
b10111011 "
b10111011 $
b10111011 %
b10100 '
#105000
b1110010 !
b0 "
b1110010 $
b0 %
b10101 '
#110000
b1110111 !
b1110111 "
b1110111 $
b1110111 %
b10110 '
#115000
b10110100 !
b0 "
b10110100 $
b0 %
b10111 '
#120000
b1001011 !
b1001011 "
b1001011 $
b1001011 %
b11000 '
#125000
b10101110 !
b0 "
b10101110 $
b0 %
b11001 '
#130000
b10000110 !
b10000110 $
b0 %
b11010 '
#135000
b111 !
b111 "
b111 $
b111 %
b11011 '
#140000
b100000 !
b0 "
b100000 $
b0 %
b11100 '
#145000
b11111101 !
b11111101 "
b11111101 $
b11111101 %
b11101 '
#150000
b10111011 !
b10111011 "
b10111011 $
b10111011 %
b11110 '
#155000
b1101100 !
b0 "
b1101100 $
b0 %
b11111 '
#160000
b100000 '
