Day13/various_mux.sv
`timescale 1ns / 1ps
//////////////////////////////////////////////////////////////////////////////////
// Company: 
// Engineer: 
// 
// Create Date: 05/07/2024 05:54:03 AM
// Design Name: 
// Module Name: various_mux
// Project Name: 
// Target Devices: 
// Tool Versions: 
// Description: 
// 
// Dependencies: 
// 
// Revision:
// Revision 0.01 - File Created
// Additional Comments:
// 
//////////////////////////////////////////////////////////////////////////////////


module various_mux(
    input wire [3:0]a_i,
    input wire [3:0]sel_i,
    
    output wire y_ter_o,
    
    output logic y_case_o,
    
    output logic y_ifelse_o,
    
    output logic y_loop_o,
    
    output wire y_aor_o
    
    );
    
    assign y_ter_o = sel_i[0] ? a_i[0] :
                     sel_i[1] ? a_i[1] :
                     sel_i[2] ? a_i[2] :
                     a_i[3];
    
    always_comb begin
    case(sel_i)
    4'b0001: y_case_o = a_i[0];
    4'b0010: y_case_o = a_i[1];
    4'b0100: y_case_o = a_i[2];
    4'b1000: y_case_o = a_i[3];
    default: y_case_o = 1'bx;
    endcase
    end
    
    always_comb begin
        if(sel_i[0]) y_ifelse_o = a_i[0];
        else if(sel_i[1]) y_ifelse_o = a_i[1];
        else if(sel_i[2]) y_ifelse_o = a_i[2];
        else if(sel_i[3]) y_ifelse_o = a_i[3];
        else  y_ifelse_o = 1'bx;  
    end
    
    always_comb begin
    y_loop_o = 0;
        for(int i=0; i<4; i++)begin
            y_loop_o = (sel_i[0] & a_i[0]) | y_loop_o;
        
        end
    end
    
      assign y_aor_o = (sel_i[0] & a_i[0]) |
                     (sel_i[1] & a_i[1]) |
                     (sel_i[2] & a_i[2]) |
                     (sel_i[3] & a_i[3]);

    
endmodule

Day13/tb_various_mux.sv
`timescale 1ns / 1ps
//////////////////////////////////////////////////////////////////////////////////
// Company: 
// Engineer: 
// 
// Create Date: 05/07/2024 05:54:35 AM
// Design Name: 
// Module Name: tb_various_mux
// Project Name: 
// Target Devices: 
// Tool Versions: 
// Description: 
// 
// Dependencies: 
// 
// Revision:
// Revision 0.01 - File Created
// Additional Comments:
// 
//////////////////////////////////////////////////////////////////////////////////

// Simple TB

module tb_various_mux ();

  
  logic [3:0] a_i;
  logic [3:0] sel_i;

  // Output using ternary operator
  logic     y_ter_o;
  // Output using case
  logic     y_case_o;
  // Ouput using if-else
  logic     y_ifelse_o;
  // Output using for loop
  logic     y_loop_o;
  // Output using and-or tree
  logic     y_aor_o;

  // Module instance
  various_mux day13(.*);

  // Stimulus
  initial begin
    for (int i =0; i<32; i++) begin
      a_i   = $urandom_range(0, 4'hF);
      sel_i = 1'b1 << $urandom_range(0, 2'h3); // one-hot
      #5;
    end
    $finish();
  end

  // VCD
  initial begin
    $dumpfile("day13.vcd");
    $dumpvars(0, tb_various_mux);
  end

endmodule

Day13/day13.vcd
$date
   Tue May  7 06:24:46 2024
$end
$version
  2018.2
$end
$timescale
  1ps
$end
$scope module tb_various_mux $end
$var reg 4 ! a_i [3:0] $end
$var reg 4 " sel_i [3:0] $end
$var reg 1 # y_ter_o $end
$var reg 1 $ y_case_o $end
$var reg 1 % y_ifelse_o $end
$var reg 1 & y_loop_o $end
$var reg 1 ' y_aor_o $end
$scope module day13 $end
$var wire 4 ( a_i [3:0] $end
$var wire 4 ) sel_i [3:0] $end
$var wire 1 * y_ter_o $end
$var reg 1 $ y_case_o $end
$var reg 1 % y_ifelse_o $end
$var reg 1 & y_loop_o $end
$var wire 1 + y_aor_o $end
$scope begin Block64_3 $end
$var reg 32 , i $end
$upscope $end
$upscope $end
$scope begin Block46_5 $end
$var reg 32 - i $end
$upscope $end
$upscope $end
$enddefinitions $end
#0
$dumpvars
b1001 !
b10 "
0#
0$
0%
0&
0'
b1001 (
b10 )
0*
0+
b100 ,
b0 -
$end
#5000
b110 !
b100 "
1#
1$
1%
0&
1'
b110 (
b100 )
1*
1+
b100 ,
b1 -
#10000
b1100 !
b1 "
0#
0$
0%
0&
0'
b1100 (
b1 )
0*
0+
b100 ,
b10 -
#15000
b10 !
b10 "
1#
1$
1%
0&
1'
b10 (
b10 )
1*
1+
b100 ,
b11 -
#20000
b1110 !
b1 "
0#
0$
0%
0&
0'
b1110 (
b1 )
0*
0+
b100 ,
b100 -
#25000
b11 !
b100 "
0&
b11 (
b100 )
0*
0+
b100 ,
b101 -
#30000
b1101 !
b100 "
1#
1$
1%
1'
b1101 (
1*
1+
b110 -
#35000
b0 !
b1000 "
0#
0$
0%
0&
0'
b0 (
b1000 )
0*
0+
b100 ,
b111 -
#40000
b1110 !
b1000 "
1#
1$
1%
1'
b1110 (
1*
1+
b1000 -
#45000
b101 !
b1000 "
0#
0$
0%
0&
0'
b101 (
0*
0+
b100 ,
b1001 -
#50000
b1001 !
b10 "
b1001 (
b10 )
0*
0+
b1010 -
#55000
b110 !
b1 "
0&
b110 (
b1 )
0*
0+
b100 ,
b1011 -
#60000
b1001 !
b1 "
1#
1$
1%
1&
1'
b1001 (
1*
1+
b100 ,
b1100 -
#65000
b11 !
b100 "
0#
0$
0%
0&
0'
b11 (
b100 )
0*
0+
b100 ,
b1101 -
#70000
b1 !
b100 "
b1 (
0*
0+
b1110 -
#75000
b1010 !
b100 "
0&
b1010 (
0*
0+
b100 ,
b1111 -
#80000
b110 !
b100 "
1#
1$
1%
1'
b110 (
1*
1+
b10000 -
#85000
b1101 !
b1000 "
0&
b1101 (
b1000 )
1*
1+
b100 ,
b10001 -
#90000
b1000 !
b1000 "
0&
b1000 (
1*
1+
b100 ,
b10010 -
#95000
b10 !
b100 "
0#
0$
0%
0'
b10 (
b100 )
0*
0+
b10011 -
#100000
b101 !
b1000 "
0&
b101 (
b1000 )
0*
0+
b100 ,
b10100 -
#105000
b101 !
b10 "
b10 )
0*
0+
b10101 -
#110000
b110 !
b1000 "
0&
b110 (
b1000 )
0*
0+
b100 ,
b10110 -
#115000
b1011 !
b1 "
1#
1$
1%
1&
1'
b1011 (
b1 )
1*
1+
b100 ,
b10111 -
#120000
b110 !
b10 "
0&
b110 (
b10 )
1*
1+
b100 ,
b11000 -
#125000
b1001 !
b10 "
0#
0$
0%
0&
0'
b1001 (
0*
0+
b100 ,
b11001 -
#130000
b1000 !
b10 "
0&
b1000 (
0*
0+
b100 ,
b11010 -
#135000
b1001 !
b1000 "
1#
1$
1%
0&
1'
b1001 (
b1000 )
1*
1+
b100 ,
b11011 -
#140000
b110 !
b100 "
0&
b110 (
b100 )
1*
1+
b100 ,
b11100 -
#145000
b1100 !
b100 "
b1100 (
1*
1+
b11101 -
#150000
b111 !
b10 "
0&
b111 (
b10 )
1*
1+
b100 ,
b11110 -
#155000
b1101 !
b10 "
0#
0$
0%
0'
b1101 (
0*
0+
b11111 -
