Day11/parallel_to_serial.sv
// Parallel to serial with valid and empty

module parallel_to_serial (
  input     wire      clk,
  input     wire      reset,

  output    wire      empty_o,
  input     wire[3:0] parallel_i,
  
  output    wire      serial_o,
  output    wire      valid_o
);

 logic [3:0]shift_ff;
 logic [3:0]nxt_shift;
 
 always_ff @(posedge clk or posedge reset)
 if(reset)
    shift_ff <= 4'h0;
 else
    shift_ff <= nxt_shift;
    
    assign nxt_shift = empty_o ? parallel_i :
                               {1'b0,shift_ff[3:1]};
        
        
    assign serial_o = shift_ff[0];
          
     logic [2:0]cnt_ff;
     logic [2:0]nxt_cnt;
     
     always_ff @(posedge clk or posedge reset)
     if(reset)
        cnt_ff <= 4'h0;
     else
        cnt_ff <= nxt_cnt;
     
         assign nxt_cnt = (cnt_ff == 3'h4)?3'h0 :
                                          cnt_ff + 3'h1;                    
     assign empty_o = (cnt_ff == 4'h0);
     
     assign valid_o = |cnt_ff;
     


endmodule

Day11/tb_parallel_to_serial.sv
`timescale 1ns / 1ps

module tb_parallel_to_serial ();

  logic      clk;
  logic      reset;

  logic      empty_o;
  logic[3:0] parallel_i;
  logic      serial_o;
  logic      valid_o;

  parallel_to_serial DAY11 (.*);

  // Clock
  always begin
    clk = 1'b1;
    #5;
    clk = 1'b0;
    #5;
  end

  // Stimulus
  initial begin
    reset <= 1'b1;
    parallel_i <= 4'h0;
    @(negedge clk);
    reset <= 1'b0;
    @(posedge clk);
    for (int i=0; i<32; i=i+1) begin
      parallel_i <= $urandom_range(0, 4'hF);
      @(posedge clk);
    end
    $finish();
  end

  // VCD
  initial begin
    $dumpfile("day11.vcd");
    $dumpvars(0, tb_parallel_to_serial);
  end

endmodule

Day11/day11.vcd
$date
   Sun May  5 15:34:26 2024
$end
$version
  2018.2
$end
$timescale
  1ps
$end
$scope module tb_parallel_to_serial $end
$var reg 1 ! clk $end
$var reg 1 " reset $end
$var reg 1 # empty_o $end
$var reg 4 $ parallel_i [3:0] $end
$var reg 1 % serial_o $end
$var reg 1 & valid_o $end
$scope module DAY11 $end
$var wire 1 ' clk $end
$var wire 1 ( reset $end
$var wire 1 ) empty_o $end
$var wire 4 * parallel_i [3:0] $end
$var wire 1 + serial_o $end
$var wire 1 , valid_o $end
$var reg 4 - shift_ff [3:0] $end
$var reg 4 . nxt_shift [3:0] $end
$var reg 3 / cnt_ff [2:0] $end
$var reg 3 0 nxt_cnt [2:0] $end
$upscope $end
$scope begin Block30_4 $end
$var reg 32 1 i $end
$upscope $end
$upscope $end
$enddefinitions $end
#0
$dumpvars
1!
1"
1#
b0 $
0%
0&
1'
1(
1)
b0 *
0+
0,
b0 -
b0 .
b0 /
b1 0
b0 1
$end
#5000
0!
0"
0'
0(
#10000
1!
0#
b1001 $
1&
1'
0)
b1001 *
1,
b1 /
b10 0
#15000
0!
0'
#20000
1!
1'
0)
1,
b10 /
b11 0
b1 1
#25000
0!
0'
#30000
1!
b110 $
1'
0)
b110 *
1,
b11 /
b100 0
b10 1
#35000
0!
0'
#40000
1!
b1110 $
1'
0)
b1110 *
1,
b100 /
b0 0
b11 1
#45000
0!
0'
#50000
1!
1#
b1100 $
0&
1'
1)
b1100 *
0,
b1100 .
b0 /
b1 0
b100 1
#55000
0!
0'
#60000
1!
0#
b100 $
1&
1'
0)
b100 *
1,
b1100 -
b110 .
b1 /
b10 0
b101 1
#65000
0!
0'
#70000
1!
b10 $
1'
0)
b10 *
1,
b110 -
b11 .
b10 /
b11 0
b110 1
#75000
0!
0'
#80000
1!
b101 $
1%
1'
0)
b101 *
1+
1,
b11 -
b1 .
b11 /
b100 0
b111 1
#85000
0!
0'
#90000
1!
b1110 $
1'
0)
b1110 *
1,
b1 -
b0 .
b100 /
b0 0
b1000 1
#95000
0!
0'
#100000
1!
1#
b1000 $
0%
0&
1'
1)
b1000 *
0+
0,
b0 -
b1000 .
b0 /
b1 0
b1001 1
#105000
0!
0'
#110000
1!
0#
b11 $
1&
1'
0)
b11 *
1,
b1000 -
b100 .
b1 /
b10 0
b1010 1
#115000
0!
0'
#120000
1!
b1010 $
1'
0)
b1010 *
1,
b100 -
b10 .
b10 /
b11 0
b1011 1
#125000
0!
0'
#130000
1!
b1101 $
1'
0)
b1101 *
1,
b10 -
b1 .
b11 /
b100 0
b1100 1
#135000
0!
0'
#140000
1!
b110 $
1%
1'
0)
b110 *
1+
1,
b1 -
b0 .
b100 /
b0 0
b1101 1
#145000
0!
0'
#150000
1!
1#
b0 $
0%
0&
1'
1)
b0 *
0+
0,
b0 -
b0 /
b1 0
b1110 1
#155000
0!
0'
#160000
1!
0#
b1011 $
1&
1'
0)
b1011 *
1,
b1 /
b10 0
b1111 1
#165000
0!
0'
#170000
1!
b1110 $
1'
0)
b1110 *
1,
b10 /
b11 0
b10000 1
#175000
0!
0'
#180000
1!
b11 $
1'
0)
b11 *
1,
b11 /
b100 0
b10001 1
#185000
0!
0'
#190000
1!
b101 $
1'
0)
b101 *
1,
b100 /
b0 0
b10010 1
#195000
0!
0'
#200000
1!
1#
b1011 $
0&
1'
1)
b1011 *
0,
b1011 .
b0 /
b1 0
b10011 1
#205000
0!
0'
#210000
1!
0#
b1001 $
1%
1&
1'
0)
b1001 *
1+
1,
b1011 -
b101 .
b1 /
b10 0
b10100 1
#215000
0!
0'
#220000
1!
b101 $
1'
0)
b101 *
1,
b101 -
b10 .
b10 /
b11 0
b10101 1
#225000
0!
0'
#230000
1!
b110 $
0%
1'
0)
b110 *
0+
1,
b10 -
b1 .
b11 /
b100 0
b10110 1
#235000
0!
0'
#240000
1!
b1000 $
1%
1'
0)
b1000 *
1+
1,
b1 -
b0 .
b100 /
b0 0
b10111 1
#245000
0!
0'
#250000
1!
1#
b1001 $
0%
0&
1'
1)
b1001 *
0+
0,
b0 -
b1001 .
b0 /
b1 0
b11000 1
#255000
0!
0'
#260000
1!
0#
b1100 $
1%
1&
1'
0)
b1100 *
1+
1,
b1001 -
b100 .
b1 /
b10 0
b11001 1
#265000
0!
0'
#270000
1!
b11 $
0%
1'
0)
b11 *
0+
1,
b100 -
b10 .
b10 /
b11 0
b11010 1
#275000
0!
0'
#280000
1!
b10 $
1'
0)
b10 *
1,
b10 -
b1 .
b11 /
b100 0
b11011 1
#285000
0!
0'
#290000
1!
b1 $
1%
1'
0)
b1 *
1+
1,
b1 -
b0 .
b100 /
b0 0
b11100 1
#295000
0!
0'
#300000
1!
1#
b1010 $
0%
0&
1'
1)
b1010 *
0+
0,
b0 -
b1010 .
b0 /
b1 0
b11101 1
#305000
0!
0'
#310000
1!
0#
1&
1'
0)
1,
b1010 -
b101 .
b1 /
b10 0
b11110 1
#315000
0!
0'
#320000
1!
1%
1'
0)
1+
1,
b101 -
b10 .
b10 /
b11 0
b11111 1
