Day10/load_cntr.sv
`timescale 1ns / 1ps
//////////////////////////////////////////////////////////////////////////////////
// Company: 
// Engineer: 
// 
// Create Date: 05/04/2024 07:53:36 PM
// Design Name: 
// Module Name: load_cntr
// Project Name: 
// Target Devices: 
// Tool Versions: 
// Description: 
// 
// Dependencies: 
// 
// Revision:
// Revision 0.01 - File Created
// Additional Comments:
// 
//////////////////////////////////////////////////////////////////////////////////


module load_cntr(
    input wire clk,
    input wire reset,
    input wire load_i,
    input wire [3:0]load_val_i,
    
    output wire [3:0]count_o
    
    );
    
    logic[3:0] load_ff;
   
      always_ff @(posedge clk or posedge reset)
        if (reset)
          load_ff <= 4'h0;
        else if (load_i)
          load_ff <= load_val_i;
    
      logic[3:0] count_ff;
      logic[3:0] nxt_count;
    
      always_ff @(posedge clk or posedge reset)
        if (reset)
          count_ff <= 4'h0;
        else
          count_ff <= nxt_count;
    
      assign nxt_count = load_i ? load_val_i :
                                  (count_ff == 4'hF) ? load_ff :
                                  count_ff + 4'h1;
    
      assign count_o = count_ff;
        
endmodule

Day10/tb_load_cntr.sv
`timescale 1ns / 1ps
//////////////////////////////////////////////////////////////////////////////////
// Company: 
// Engineer: 
// 
// Create Date: 05/05/2024 09:42:57 AM
// Design Name: 
// Module Name: tb_load_cntr
// Project Name: 
// Target Devices: 
// Tool Versions: 
// Description: 
// 
// Dependencies: 
// 
// Revision:
// Revision 0.01 - File Created
// Additional Comments:
// 
//////////////////////////////////////////////////////////////////////////////////


module tb_load_cntr();

        
  logic          clk;
  logic          reset;
  logic          load_i;
  logic[3:0]     load_val_i;

  logic[3:0]     count_o;

  load_cntr day10 (.*);

  always begin
    clk = 1'b1;
    #5;
    clk = 1'b0;
    #5;
  end
  
   int cycles;
   initial begin
     reset <= 1'b1;
     load_i <= 1'b0;
     load_val_i <= 4'h0;
     @(posedge clk);
     reset <= 1'b0;
     for (int i=0; i<3; i=i+1) begin
       load_i <= 1;
       load_val_i <= 3*i;
       cycles = 4'hF - load_val_i[3:0];
       @(posedge clk);
       load_i <= 0;
       while (cycles) begin
         cycles = cycles - 1;
         @(posedge clk);
       end
     end
     $finish();
   end
 
   initial begin
     $dumpfile("day10.vcd");
     $dumpvars(2, tb_load_cntr);
   end
        
endmodule

Day10/day10.vcd
$date
   Sun May  5 09:45:48 2024
$end
$version
  2018.2
$end
$timescale
  1ps
$end
$scope module tb_load_cntr $end
$var reg 1 ! clk $end
$var reg 1 " reset $end
$var reg 1 # load_i $end
$var reg 4 $ load_val_i [3:0] $end
$var reg 4 % count_o [3:0] $end
$var reg 32 & cycles $end
$scope module day10 $end
$var wire 1 ' clk $end
$var wire 1 ( reset $end
$var wire 1 ) load_i $end
$var wire 4 * load_val_i [3:0] $end
$var wire 4 + count_o [3:0] $end
$var reg 4 , load_ff [3:0] $end
$var reg 4 - count_ff [3:0] $end
$var reg 4 . nxt_count [3:0] $end
$upscope $end
$scope begin Block49_4 $end
$var reg 32 / i $end
$upscope $end
$upscope $end
$enddefinitions $end
#0
$dumpvars
1!
1"
0#
b0 $
b0 %
b0 &
1'
1(
0)
b0 *
b0 +
b0 ,
b0 -
b1 .
b0 /
$end
#5000
0!
0'
#10000
1!
0"
1#
b0 $
b1111 &
1'
0(
1)
b0 ,
b0 -
b0 .
b0 /
#15000
0!
0'
#20000
1!
0#
b1110 &
1'
0)
b0 ,
b0 -
b1 .
#25000
0!
0'
#30000
1!
b1 %
b1101 &
1'
b1 +
b1 -
b10 .
#35000
0!
0'
#40000
1!
b10 %
b1100 &
1'
b10 +
b10 -
b11 .
#45000
0!
0'
#50000
1!
b11 %
b1011 &
1'
b11 +
b11 -
b100 .
#55000
0!
0'
#60000
1!
b100 %
b1010 &
1'
b100 +
b100 -
b101 .
#65000
0!
0'
#70000
1!
b101 %
b1001 &
1'
b101 +
b101 -
b110 .
#75000
0!
0'
#80000
1!
b110 %
b1000 &
1'
b110 +
b110 -
b111 .
#85000
0!
0'
#90000
1!
b111 %
b111 &
1'
b111 +
b111 -
b1000 .
#95000
0!
0'
#100000
1!
b1000 %
b110 &
1'
b1000 +
b1000 -
b1001 .
#105000
0!
0'
#110000
1!
b1001 %
b101 &
1'
b1001 +
b1001 -
b1010 .
#115000
0!
0'
#120000
1!
b1010 %
b100 &
1'
b1010 +
b1010 -
b1011 .
#125000
0!
0'
#130000
1!
b1011 %
b11 &
1'
b1011 +
b1011 -
b1100 .
#135000
0!
0'
#140000
1!
b1100 %
b10 &
1'
b1100 +
b1100 -
b1101 .
#145000
0!
0'
#150000
1!
b1101 %
b1 &
1'
b1101 +
b1101 -
b1110 .
#155000
0!
0'
#160000
1!
b1110 %
b0 &
1'
b1110 +
b1110 -
b1111 .
#165000
0!
0'
#170000
1!
1#
b11 $
b1111 %
b1111 &
1'
1)
b11 *
b1111 +
b1111 -
b11 .
b1 /
#175000
0!
0'
#180000
1!
0#
b11 %
b1110 &
1'
0)
b11 +
b11 ,
b11 -
b100 .
#185000
0!
0'
#190000
1!
b100 %
b1101 &
1'
b100 +
b100 -
b101 .
#195000
0!
0'
#200000
1!
b101 %
b1100 &
1'
b101 +
b101 -
b110 .
#205000
0!
0'
#210000
1!
b110 %
b1011 &
1'
b110 +
b110 -
b111 .
#215000
0!
0'
#220000
1!
b111 %
b1010 &
1'
b111 +
b111 -
b1000 .
#225000
0!
0'
#230000
1!
b1000 %
b1001 &
1'
b1000 +
b1000 -
b1001 .
#235000
0!
0'
#240000
1!
b1001 %
b1000 &
1'
b1001 +
b1001 -
b1010 .
#245000
0!
0'
#250000
1!
b1010 %
b111 &
1'
b1010 +
b1010 -
b1011 .
#255000
0!
0'
#260000
1!
b1011 %
b110 &
1'
b1011 +
b1011 -
b1100 .
#265000
0!
0'
#270000
1!
b1100 %
b101 &
1'
b1100 +
b1100 -
b1101 .
#275000
0!
0'
#280000
1!
b1101 %
b100 &
1'
b1101 +
b1101 -
b1110 .
#285000
0!
0'
#290000
1!
b1110 %
b11 &
1'
b1110 +
b1110 -
b1111 .
#295000
0!
0'
#300000
1!
b1111 %
b10 &
1'
b1111 +
b1111 -
b11 .
#305000
0!
0'
#310000
1!
b11 %
b1 &
1'
b11 +
b11 -
b100 .
#315000
0!
0'
#320000
1!
b100 %
b0 &
1'
b100 +
b100 -
b101 .
#325000
0!
0'
#330000
1!
1#
b110 $
b101 %
b1100 &
1'
1)
b110 *
b101 +
b101 -
b110 .
b10 /
#335000
0!
0'
#340000
1!
0#
b110 %
b1011 &
1'
0)
b110 +
b110 ,
b110 -
b111 .
#345000
0!
0'
#350000
1!
b111 %
b1010 &
1'
b111 +
b111 -
b1000 .
#355000
0!
0'
#360000
1!
b1000 %
b1001 &
1'
b1000 +
b1000 -
b1001 .
#365000
0!
0'
#370000
1!
b1001 %
b1000 &
1'
b1001 +
b1001 -
b1010 .
#375000
0!
0'
#380000
1!
b1010 %
b111 &
1'
b1010 +
b1010 -
b1011 .
#385000
0!
0'
#390000
1!
b1011 %
b110 &
1'
b1011 +
b1011 -
b1100 .
#395000
0!
0'
#400000
1!
b1100 %
b101 &
1'
b1100 +
b1100 -
b1101 .
#405000
0!
0'
#410000
1!
b1101 %
b100 &
1'
b1101 +
b1101 -
b1110 .
#415000
0!
0'
#420000
1!
b1110 %
b11 &
1'
b1110 +
b1110 -
b1111 .
#425000
0!
0'
#430000
1!
b1111 %
b10 &
1'
b1111 +
b1111 -
b110 .
#435000
0!
0'
#440000
1!
b110 %
b1 &
1'
b110 +
b110 -
b111 .
#445000
0!
0'
#450000
1!
b111 %
b0 &
1'
b111 +
b111 -
b1000 .
