Day1/mux.sv
`timescale 1ns / 1ps
//////////////////////////////////////////////////////////////////////////////////
// Company: 
// Engineer: 
// 
// Create Date: 05/03/2024 05:36:53 AM
// Design Name: 
// Module Name: mux
// Project Name: 
// Target Devices: 
// Tool Versions: 
// Description: 
// 
// Dependencies: 
// 
// Revision:
// Revision 0.01 - File Created
// Additional Comments:
// 
//////////////////////////////////////////////////////////////////////////////////


module mux(
    input wire [7:0] a_i,
    input wire [7:0] b_i,
    input wire sel_i,
    output wire [7:0] y_o
    );
    
    assign y_o = sel_i ? a_i : b_i;
    
endmodule

tb_mux.sv
`timescale 1ns / 1ps
//////////////////////////////////////////////////////////////////////////////////
// Company: 
// Engineer: 
// 
// Create Date: 05/03/2024 05:39:27 AM
// Design Name: 
// Module Name: tb_mux
// Project Name: 
// Target Devices: 
// Tool Versions: 
// Description: 
// 
// Dependencies: 
// 
// Revision:
// Revision 0.01 - File Created
// Additional Comments:
// 
//////////////////////////////////////////////////////////////////////////////////


module tb_mux();

logic [7:0] a_i;
logic [7:0] b_i;
logic sel_i;
logic [7:0] y_o;

    mux mux_1(.*);
    
    initial begin
    for (int i = 0; i <10; i=i++)begin
    a_i = $urandom_range (0,8'hff);
    b_i = $urandom_range (0,8'hff);
    sel_i = $random%2;
    #5;
    end
    end 
  
  initial begin
      $dumpfile("mux.vcd");
      $dumpvars(0, tb_mux);
    end


endmodule

Day01/mux.vcd
$date
   Fri May  3 06:04:45 2024
$end
$version
  2018.2
$end
$timescale
  1ps
$end
$scope module tb_mux $end
$var reg 8 ! a_i [7:0] $end
$var reg 8 " b_i [7:0] $end
$var reg 1 # sel_i $end
$var reg 8 $ y_o [7:0] $end
$scope module mux_1 $end
$var wire 8 % a_i [7:0] $end
$var wire 8 & b_i [7:0] $end
$var wire 1 ' sel_i $end
$var wire 8 ( y_o [7:0] $end
$upscope $end
$scope begin Block33_1 $end
$var reg 32 ) i $end
$upscope $end
$upscope $end
$enddefinitions $end
#0
$dumpvars
b11100011 !
b1011 "
0#
b1011 $
b11100011 %
b1011 &
0'
b1011 (
b0 )
$end
#5000
b11010100 !
b11110110 "
1#
b11010100 $
b11010100 %
b11110110 &
1'
b11010100 (
b0 )
#10000
b11000101 !
b11000001 "
1#
b11000101 $
b11000101 %
b11000001 &
b11000101 (
b0 )
#15000
b1000011 !
b10101000 "
1#
b1000011 $
b1000011 %
b10101000 &
b1000011 (
b0 )
#20000
b11001101 !
b10111 "
b11001101 $
b11001101 %
b10111 &
b11001101 (
b0 )
#25000
b10011111 !
b10010010 "
b10011111 $
b10011111 %
b10010010 &
b10011111 (
b0 )
#30000
b11011000 !
b11100010 "
1#
b11011000 $
b11011000 %
b11100010 &
b11011000 (
b0 )
#35000
b111010 !
b10100101 "
0#
b10100101 $
b111010 %
b10100101 &
0'
b10100101 (
b0 )
#40000
b11111001 !
b11011001 "
1#
b11111001 $
b11111001 %
b11011001 &
1'
b11111001 (
b0 )
#45000
b110111 !
b11010001 "
b110111 $
b110111 %
b11010001 &
b110111 (
b0 )
#50000
b10111011 !
b1110010 "
0#
b1110010 $
b10111011 %
b1110010 &
0'
b1110010 (
b0 )
#55000
b1110111 !
b10110100 "
1#
b1110111 $
b1110111 %
b10110100 &
1'
b1110111 (
b0 )
#60000
b1001011 !
b10101110 "
b1001011 $
b1001011 %
b10101110 &
b1001011 (
b0 )
#65000
b10000110 !
b111 "
0#
b111 $
b10000110 %
b111 &
0'
b111 (
b0 )
#70000
b100000 !
b11111101 "
1#
b100000 $
b100000 %
b11111101 &
1'
b100000 (
b0 )
#75000
b10111011 !
b1101100 "
0#
b1101100 $
b10111011 %
b1101100 &
0'
b1101100 (
b0 )
#80000
b10101011 !
b1000001 "
1#
b10101011 $
b10101011 %
b1000001 &
1'
b10101011 (
b0 )
#85000
b1110011 !
b11001100 "
0#
b11001100 $
b1110011 %
b11001100 &
0'
b11001100 (
b0 )
#90000
b111110 !
b101110 "
1#
b111110 $
b111110 %
b101110 &
1'
b111110 (
b0 )
#95000
b111000 !
b11101010 "
1#
b111000 $
b111000 %
b11101010 &
b111000 (
b0 )
#100000
b1110000 !
b10101011 "
0#
b10101011 $
b1110000 %
b10101011 &
0'
b10101011 (
b0 )
#105000
b10110110 !
b10101110 "
1#
b10110110 $
b10110110 %
b10101110 &
1'
b10110110 (
b0 )
#110000
b11011001 !
b11101110 "
0#
b11101110 $
b11011001 %
b11101110 &
0'
b11101110 (
b0 )
#115000
b10011000 !
b1001001 "
b1001001 $
b10011000 %
b1001001 &
b1001001 (
b0 )
#120000
b10011001 !
b1001110 "
b1001110 $
b10011001 %
b1001110 &
b1001110 (
b0 )
#125000
b11111000 !
b1110010 "
1#
b11111000 $
b11111000 %
b1110010 &
1'
b11111000 (
b0 )
#130000
b111100 !
b10010000 "
0#
b10010000 $
b111100 %
b10010000 &
0'
b10010000 (
b0 )
#135000
b10111100 !
b11010101 "
1#
b10111100 $
b10111100 %
b11010101 &
1'
b10111100 (
b0 )
#140000
b11011111 !
b10110100 "
1#
b11011111 $
b11011111 %
b10110100 &
b11011111 (
b0 )
#145000
b1001000 !
b11011 "
1#
b1001000 $
b1001000 %
b11011 &
b1001000 (
b0 )
#150000
b1000100 !
b100 "
1#
b1000100 $
b1000100 %
b100 &
b1000100 (
b0 )
#155000
b11110001 !
b100011 "
0#
b100011 $
b11110001 %
b100011 &
0'
b100011 (
b0 )
#160000
b10111000 !
b111001 "
b111001 $
b10111000 %
b111001 &
b111001 (
b0 )
#165000
b111111 !
b11111100 "
b11111100 $
b111111 %
b11111100 &
b11111100 (
b0 )
#170000
b111101 !
b110000 "
b110000 $
b111101 %
b110000 &
b110000 (
b0 )
#175000
b100000 !
b11110101 "
1#
b100000 $
b100000 %
b11110101 &
1'
b100000 (
b0 )
#180000
b1101001 !
b1011111 "
0#
b1011111 $
b1101001 %
b1011111 &
0'
b1011111 (
b0 )
#185000
b11110001 !
b10100110 "
1#
b11110001 $
b11110001 %
b10100110 &
1'
b11110001 (
b0 )
#190000
b10001111 !
b10001 "
1#
b10001111 $
b10001111 %
b10001 &
b10001111 (
b0 )
#195000
b10011011 !
b11111000 "
1#
b10011011 $
b10011011 %
b11111000 &
b10011011 (
b0 )
#200000
b1110000 !
b10001100 "
b1110000 $
b1110000 %
b10001100 &
b1110000 (
b0 )
#205000
b10011110 !
b11111111 "
1#
b10011110 $
b10011110 %
b11111111 &
b10011110 (
b0 )
#210000
b10011110 !
b111001 "
0#
b111001 $
b111001 &
0'
b111001 (
b0 )
#215000
b11110111 !
b1110 "
b1110 $
b11110111 %
b1110 &
b1110 (
b0 )
#220000
b11000101 !
b10010101 "
1#
b11000101 $
b11000101 %
b10010101 &
1'
b11000101 (
b0 )
#225000
b1110 !
b1100011 "
1#
b1110 $
b1110 %
b1100011 &
b1110 (
b0 )
#230000
b11001110 !
b101 "
b11001110 $
b11001110 %
b101 &
b11001110 (
b0 )
#235000
b1110010 !
b10010100 "
0#
b10010100 $
b1110010 %
b10010100 &
0'
b10010100 (
b0 )
#240000
b10011011 !
b10000000 "
b10000000 $
b10011011 %
b10000000 &
b10000000 (
b0 )
#245000
b11110111 !
b1101001 "
b1101001 $
b11110111 %
b1101001 &
b1101001 (
b0 )
#250000
b10000101 !
b1101001 "
b10000101 %
b1101001 (
b0 )
#255000
b11111101 !
b100000 "
b100000 $
b11111101 %
b100000 &
b100000 (
b0 )
#260000
b11101001 !
b11110101 "
1#
b11101001 $
b11101001 %
b11110101 &
1'
b11101001 (
b0 )
#265000
b10001010 !
b1101111 "
0#
b1101111 $
b10001010 %
b1101111 &
0'
b1101111 (
b0 )
#270000
b1011110 !
b10000111 "
b10000111 $
b1011110 %
b10000111 &
b10000111 (
b0 )
#275000
b10001111 !
b1001000 "
1#
b10001111 $
b10001111 %
b1001000 &
1'
b10001111 (
b0 )
#280000
b1111100 !
b11001 "
b1111100 $
b1111100 %
b11001 &
b1111100 (
b0 )
#285000
b10110111 !
b11011011 "
0#
b11011011 $
b10110111 %
b11011011 &
0'
b11011011 (
b0 )
#290000
b10100001 !
b1000110 "
b1000110 $
b10100001 %
b1000110 &
b1000110 (
b0 )
#295000
b100011 !
b11101 "
b11101 $
b100011 %
b11101 &
b11101 (
b0 )
#300000
b1100000 !
b11011010 "
b11011010 $
b1100000 %
b11011010 &
b11011010 (
b0 )
#305000
b11111000 !
b1 "
b1 $
b11111000 %
b1 &
b1 (
b0 )
#310000
b100000 !
b11011 "
1#
b100000 $
b100000 %
b11011 &
1'
b100000 (
b0 )
#315000
b11110 !
b10000000 "
1#
b11110 $
b11110 %
b10000000 &
b11110 (
b0 )
#320000
b11110101 !
b10111 "
b11110101 $
b11110101 %
b10111 &
b11110101 (
b0 )
#325000
b10000001 !
b10110 "
b10000001 $
b10000001 %
b10110 &
b10000001 (
b0 )
#330000
b110010 !
b10100000 "
1#
b110010 $
b110010 %
b10100000 &
b110010 (
b0 )
#335000
b10010110 !
b101000 "
0#
b101000 $
b10010110 %
b101000 &
0'
b101000 (
b0 )
#340000
b10110111 !
b11000 "
b11000 $
b10110111 %
b11000 &
b11000 (
b0 )
#345000
b111110 !
b11101001 "
1#
b111110 $
b111110 %
b11101001 &
1'
b111110 (
b0 )
#350000
b10111000 !
b11010100 "
b10111000 $
b10111000 %
b11010100 &
b10111000 (
b0 )
#355000
b10001 !
b1101111 "
b10001 $
b10001 %
b1101111 &
b10001 (
b0 )
#360000
b11101100 !
b1001111 "
0#
b1001111 $
b11101100 %
b1001111 &
0'
b1001111 (
b0 )
#365000
b1011000 !
b10100100 "
b10100100 $
b1011000 %
b10100100 &
b10100100 (
b0 )
#370000
b100100 !
b1101010 "
1#
b100100 $
b100100 %
b1101010 &
1'
b100100 (
b0 )
#375000
b10011 !
b10000 "
b10011 $
b10011 %
b10000 &
b10011 (
b0 )
#380000
b10111001 !
b1101100 "
0#
b1101100 $
b10111001 %
b1101100 &
0'
b1101100 (
b0 )
#385000
b10110101 !
b11011101 "
1#
b10110101 $
b10110101 %
b11011101 &
1'
b10110101 (
b0 )
#390000
b11010110 !
b11001000 "
1#
b11010110 $
b11010110 %
b11001000 &
b11010110 (
b0 )
#395000
b11101110 !
b10001111 "
0#
b10001111 $
b11101110 %
b10001111 &
0'
b10001111 (
b0 )
#400000
b110100 !
b10100011 "
1#
b110100 $
b110100 %
b10100011 &
1'
b110100 (
b0 )
#405000
b1101101 !
b1010 "
b1101101 $
b1101101 %
b1010 &
b1101101 (
b0 )
#410000
b1101011 !
b1011011 "
1#
b1101011 $
b1101011 %
b1011011 &
b1101011 (
b0 )
#415000
b10011010 !
b10100000 "
0#
b10100000 $
b10011010 %
b10100000 &
0'
b10100000 (
b0 )
#420000
b11111110 !
b111 "
1#
b11111110 $
b11111110 %
b111 &
1'
b11111110 (
b0 )
#425000
b10101010 !
b1101001 "
1#
b10101010 $
b10101010 %
b1101001 &
b10101010 (
b0 )
#430000
b1100010 !
b1000100 "
0#
b1000100 $
b1100010 %
b1000100 &
0'
b1000100 (
b0 )
#435000
b1001 !
b1100000 "
b1100000 $
b1001 %
b1100000 &
b1100000 (
b0 )
#440000
b1001011 !
b10110100 "
b10110100 $
b1001011 %
b10110100 &
b10110100 (
b0 )
#445000
b11001001 !
b10101101 "
b10101101 $
b11001001 %
b10101101 &
b10101101 (
b0 )
#450000
b11111000 !
b11010011 "
1#
b11111000 $
b11111000 %
b11010011 &
1'
b11111000 (
b0 )
#455000
b1101 !
b1000100 "
b1101 $
b1101 %
b1000100 &
b1101 (
b0 )
#460000
b10000111 !
b11010111 "
0#
b11010111 $
b10000111 %
b11010111 &
0'
b11010111 (
b0 )
#465000
b11110001 !
b1111111 "
b1111111 $
b11110001 %
b1111111 &
b1111111 (
b0 )
#470000
b10101010 !
b11111111 "
1#
b10101010 $
b10101010 %
b11111111 &
1'
b10101010 (
b0 )
#475000
b11000011 !
b110001 "
b11000011 $
b11000011 %
b110001 &
b11000011 (
b0 )
#480000
b11010110 !
b10110101 "
b11010110 $
b11010110 %
b10110101 &
b11010110 (
b0 )
#485000
b10110000 !
b10000000 "
1#
b10110000 $
b10110000 %
b10000000 &
b10110000 (
b0 )
#490000
b10110100 !
b1110100 "
b10110100 $
b10110100 %
b1110100 &
b10110100 (
b0 )
#495000
b10110001 !
b10001010 "
0#
b10001010 $
b10110001 %
b10001010 &
0'
b10001010 (
b0 )
#500000
b101001 !
b1100001 "
1#
b101001 $
b101001 %
b1100001 &
1'
b101001 (
b0 )
#505000
b1010 !
b11011101 "
b1010 $
b1010 %
b11011101 &
b1010 (
b0 )
#510000
b11010101 !
b10111011 "
1#
b11010101 $
b11010101 %
b10111011 &
b11010101 (
b0 )
#515000
b1100111 !
b11111110 "
0#
b11111110 $
b1100111 %
b11111110 &
0'
b11111110 (
b0 )
#520000
b11100 !
b1110001 "
b1110001 $
b11100 %
b1110001 &
b1110001 (
b0 )
#525000
b11011011 !
b11110010 "
b11110010 $
b11011011 %
b11110010 &
b11110010 (
b0 )
#530000
b101100 !
b1000010 "
b1000010 $
b101100 %
b1000010 &
b1000010 (
b0 )
#535000
b11110000 !
b1001000 "
b1001000 $
b11110000 %
b1001000 &
b1001000 (
b0 )
#540000
b10110011 !
b11001100 "
b11001100 $
b10110011 %
b11001100 &
b11001100 (
b0 )
#545000
b111010 !
b11011111 "
b11011111 $
b111010 %
b11011111 &
b11011111 (
b0 )
#550000
b1110 !
b101011 "
1#
b1110 $
b1110 %
b101011 &
1'
b1110 (
b0 )
#555000
b101000 !
b11000010 "
1#
b101000 $
b101000 %
b11000010 &
b101000 (
b0 )
#560000
b11110111 !
b1100010 "
1#
b11110111 $
b11110111 %
b1100010 &
b11110111 (
b0 )
#565000
b10100001 !
b101 "
1#
b10100001 $
b10100001 %
b101 &
b10100001 (
b0 )
#570000
b10001101 !
b11001001 "
1#
b10001101 $
b10001101 %
b11001001 &
b10001101 (
b0 )
#575000
b11000111 !
b10000100 "
0#
b10000100 $
b11000111 %
b10000100 &
0'
b10000100 (
b0 )
#580000
b101100 !
b1101001 "
1#
b101100 $
b101100 %
b1101001 &
1'
b101100 (
b0 )
#585000
b10001010 !
b10111001 "
1#
b10001010 $
b10001010 %
b10111001 &
b10001010 (
b0 )
#590000
b110010 !
b1010001 "
0#
b1010001 $
b110010 %
b1010001 &
0'
b1010001 (
b0 )
#595000
b111110 !
b1011110 "
b1011110 $
b111110 %
b1011110 &
b1011110 (
b0 )
#600000
b10111010 !
b11001000 "
1#
b10111010 $
b10111010 %
b11001000 &
1'
b10111010 (
b0 )
#605000
b11000 !
b11101101 "
1#
b11000 $
b11000 %
b11101101 &
b11000 (
b0 )
#610000
b11001 !
b1010110 "
0#
b1010110 $
b11001 %
b1010110 &
0'
b1010110 (
b0 )
#615000
b1001011 !
b11010100 "
1#
b1001011 $
b1001011 %
b11010100 &
1'
b1001011 (
b0 )
#620000
b11110 !
b1100011 "
1#
b11110 $
b11110 %
b1100011 &
b11110 (
b0 )
#625000
b11000001 !
b110111 "
1#
b11000001 $
b11000001 %
b110111 &
b11000001 (
b0 )
#630000
b10111001 !
b1100 "
b10111001 $
b10111001 %
b1100 &
b10111001 (
b0 )
#635000
b1011 !
b11010111 "
0#
b11010111 $
b1011 %
b11010111 &
0'
b11010111 (
b0 )
#640000
b1110000 !
b11001100 "
b11001100 $
b1110000 %
b11001100 &
b11001100 (
b0 )
#645000
b1111 !
b101001 "
b101001 $
b1111 %
b101001 &
b101001 (
b0 )
#650000
b11011001 !
b11010 "
1#
b11011001 $
b11011001 %
b11010 &
1'
b11011001 (
b0 )
#655000
b1 !
b1001001 "
0#
b1001001 $
b1 %
b1001001 &
0'
b1001001 (
b0 )
#660000
b11100111 !
b10000 "
b10000 $
b11100111 %
b10000 &
b10000 (
b0 )
#665000
b1110010 !
b11000000 "
b11000000 $
b1110010 %
b11000000 &
b11000000 (
b0 )
#670000
b101010 !
b1110011 "
1#
b101010 $
b101010 %
b1110011 &
1'
b101010 (
b0 )
#675000
b1001 !
b10001 "
1#
b1001 $
b1001 %
b10001 &
b1001 (
b0 )
#680000
b10000011 !
b1111011 "
0#
b1111011 $
b10000011 %
b1111011 &
0'
b1111011 (
b0 )
#685000
b11010001 !
b10101110 "
b10101110 $
b11010001 %
b10101110 &
b10101110 (
b0 )
#690000
b11101111 !
b11011010 "
1#
b11101111 $
b11101111 %
b11011010 &
1'
b11101111 (
b0 )
#695000
b10111111 !
b1110010 "
0#
b1110010 $
b10111111 %
b1110010 &
0'
b1110010 (
b0 )
#700000
b1010110 !
b10010001 "
b10010001 $
b1010110 %
b10010001 &
b10010001 (
b0 )
#705000
b100000 !
b1000101 "
b1000101 $
b100000 %
b1000101 &
b1000101 (
b0 )
#710000
b1101011 !
b11100000 "
1#
b1101011 $
b1101011 %
b11100000 &
1'
b1101011 (
b0 )
#715000
b10110111 !
b11000001 "
0#
b11000001 $
b10110111 %
b11000001 &
0'
b11000001 (
b0 )
#720000
b1110001 !
b11011000 "
b11011000 $
b1110001 %
b11011000 &
b11011000 (
b0 )
#725000
b110 !
b11011100 "
1#
b110 $
b110 %
b11011100 &
1'
b110 (
b0 )
#730000
b10111000 !
b10111110 "
0#
b10111110 $
b10111000 %
b10111110 &
0'
b10111110 (
b0 )
#735000
b10011110 !
b101001 "
1#
b10011110 $
b10011110 %
b101001 &
1'
b10011110 (
b0 )
#740000
b10010110 !
b10100100 "
b10010110 $
b10010110 %
b10100100 &
b10010110 (
b0 )
#745000
b101 !
b1001110 "
1#
b101 $
b101 %
b1001110 &
b101 (
b0 )
#750000
b1100010 !
b10100011 "
b1100010 $
b1100010 %
b10100011 &
b1100010 (
b0 )
#755000
b1110111 !
b11111000 "
1#
b1110111 $
b1110111 %
b11111000 &
b1110111 (
b0 )
#760000
b1001000 !
b1111100 "
0#
b1111100 $
b1001000 %
b1111100 &
0'
b1111100 (
b0 )
#765000
b1000110 !
b10101010 "
b10101010 $
b1000110 %
b10101010 &
b10101010 (
b0 )
#770000
b100000 !
b10111101 "
b10111101 $
b100000 %
b10111101 &
b10111101 (
b0 )
#775000
b10100011 !
b1101000 "
1#
b10100011 $
b10100011 %
b1101000 &
1'
b10100011 (
b0 )
#780000
b111010 !
b11101001 "
0#
b11101001 $
b111010 %
b11101001 &
0'
b11101001 (
b0 )
#785000
b10010 !
b1011010 "
b1011010 $
b10010 %
b1011010 &
b1011010 (
b0 )
#790000
b10100111 !
b10110101 "
1#
b10100111 $
b10100111 %
b10110101 &
1'
b10100111 (
b0 )
#795000
b11000010 !
b11100001 "
b11000010 $
b11000010 %
b11100001 &
b11000010 (
b0 )
#800000
b10011111 !
b11010100 "
0#
b11010100 $
b10011111 %
b11010100 &
0'
b11010100 (
b0 )
#805000
b111011 !
b1000110 "
b1000110 $
b111011 %
b1000110 &
b1000110 (
b0 )
#810000
b10001010 !
b11111101 "
b11111101 $
b10001010 %
b11111101 &
b11111101 (
b0 )
#815000
b100111 !
b101001 "
1#
b100111 $
b100111 %
b101001 &
1'
b100111 (
b0 )
#820000
b11010001 !
b1100010 "
1#
b11010001 $
b11010001 %
b1100010 &
b11010001 (
b0 )
#825000
b1101111 !
b1011011 "
0#
b1011011 $
b1101111 %
b1011011 &
0'
b1011011 (
b0 )
#830000
b1011111 !
b10010110 "
b10010110 $
b1011111 %
b10010110 &
b10010110 (
b0 )
#835000
b10000100 !
b110000 "
b110000 $
b10000100 %
b110000 &
b110000 (
b0 )
#840000
b11111000 !
b11110011 "
1#
b11111000 $
b11111000 %
b11110011 &
1'
b11111000 (
b0 )
#845000
b10001100 !
b1010111 "
b10001100 $
b10001100 %
b1010111 &
b10001100 (
b0 )
#850000
b10001001 !
b10000 "
0#
b10000 $
b10001001 %
b10000 &
0'
b10000 (
b0 )
#855000
b10000111 !
b10000001 "
b10000001 $
b10000111 %
b10000001 &
b10000001 (
b0 )
#860000
b100 !
b10011 "
b10011 $
b100 %
b10011 &
b10011 (
b0 )
#865000
b11011000 !
b10001101 "
1#
b11011000 $
b11011000 %
b10001101 &
1'
b11011000 (
b0 )
#870000
b100100 !
b1100000 "
0#
b1100000 $
b100100 %
b1100000 &
0'
b1100000 (
b0 )
#875000
b1111 !
b101000 "
b101000 $
b1111 %
b101000 &
b101000 (
b0 )
#880000
b1110011 !
b11100111 "
1#
b1110011 $
b1110011 %
b11100111 &
1'
b1110011 (
b0 )
#885000
b10110101 !
b10010111 "
0#
b10010111 $
b10110101 %
b10010111 &
0'
b10010111 (
b0 )
#890000
b1000111 !
b11000100 "
b11000100 $
b1000111 %
b11000100 &
b11000100 (
b0 )
#895000
b10111111 !
b10111011 "
b10111011 $
b10111111 %
b10111011 &
b10111011 (
b0 )
#900000
b10101100 !
b1110101 "
1#
b10101100 $
b10101100 %
b1110101 &
1'
b10101100 (
b0 )
#905000
b1010010 !
b11110011 "
0#
b11110011 $
b1010010 %
b11110011 &
0'
b11110011 (
b0 )
#910000
b111001 !
b10010 "
1#
b111001 $
b111001 %
b10010 &
1'
b111001 (
b0 )
#915000
b10101110 !
b11100101 "
b10101110 $
b10101110 %
b11100101 &
b10101110 (
b0 )
#920000
b10000111 !
b1 "
0#
b1 $
b10000111 %
b1 &
0'
b1 (
b0 )
#925000
b11011001 !
b11000000 "
b11000000 $
b11011001 %
b11000000 &
b11000000 (
b0 )
#930000
b10011 !
b10000111 "
b10000111 $
b10011 %
b10000111 &
b10000111 (
b0 )
#935000
b10100110 !
b10011010 "
b10011010 $
b10100110 %
b10011010 &
b10011010 (
b0 )
#940000
b10001000 !
b1111111 "
1#
b10001000 $
b10001000 %
b1111111 &
1'
b10001000 (
b0 )
#945000
b1011010 !
b10011011 "
0#
b10011011 $
b1011010 %
b10011011 &
0'
b10011011 (
b0 )
#950000
b110 !
b0 "
b0 $
b110 %
b0 &
b0 (
b0 )
#955000
b110101 !
b10001111 "
b10001111 $
b110101 %
b10001111 &
b10001111 (
b0 )
#960000
b1111111 !
b10010000 "
b10010000 $
b1111111 %
b10010000 &
b10010000 (
b0 )
#965000
b101010 !
b10000110 "
1#
b101010 $
b101010 %
b10000110 &
1'
b101010 (
b0 )
#970000
b10010000 !
b1100000 "
1#
b10010000 $
b10010000 %
b1100000 &
b10010000 (
b0 )
#975000
b10101 !
b10000 "
b10101 $
b10101 %
b10000 &
b10101 (
b0 )
#980000
b11110000 !
b111111 "
0#
b111111 $
b11110000 %
b111111 &
0'
b111111 (
b0 )
#985000
b10010110 !
b10000000 "
1#
b10010110 $
b10010110 %
b10000000 &
1'
b10010110 (
b0 )
#990000
b10011111 !
b10101011 "
b10011111 $
b10011111 %
b10101011 &
b10011111 (
b0 )
#995000
b10010000 !
b10001111 "
1#
b10010000 $
b10010000 %
b10001111 &
b10010000 (
b0 )
#1000000
b11101010 !
b100110 "
0#
b100110 $
b11101010 %
b100110 &
0'
b100110 (
b0 )
