Day5/odd_counter.sv
`timescale 1ns / 1ps
//////////////////////////////////////////////////////////////////////////////////
// Company: 
// Engineer: 
// 
// Create Date: 05/04/2024 07:10:13 AM
// Design Name: 
// Module Name: odd_counter
// Project Name: 
// Target Devices: 
// Tool Versions: 
// Description: 
// 
// Dependencies: 
// 
// Revision:
// Revision 0.01 - File Created
// Additional Comments:
// 
//////////////////////////////////////////////////////////////////////////////////


module odd_counter(
    input wire clk,
    input wire reset,
    
    output logic [7:0] od_counter
    );
    
    logic [7:0]next_cnt;
    
    always_ff @(posedge clk or posedge reset)
    if(reset)
    od_counter <= 8'h1;
    else 
    od_counter <= next_cnt;
    
    assign next_cnt= od_counter + 2'h2;
    
endmodule

Day5/tb_od_counter.sv
`timescale 1ns / 1ps
//////////////////////////////////////////////////////////////////////////////////
// Company: 
// Engineer: 
// 
// Create Date: 05/04/2024 07:13:02 AM
// Design Name: 
// Module Name: tb_od_counter
// Project Name: 
// Target Devices: 
// Tool Versions: 
// Description: 
// 
// Dependencies: 
// 
// Revision:
// Revision 0.01 - File Created
// Additional Comments:
// 
//////////////////////////////////////////////////////////////////////////////////


module tb_od_counter();

logic clk,reset;
logic [7:0] od_counter;

odd_counter day5(.*);

always begin
clk= 1'b0;
#5;
clk=1'b1;
#5;
end

  initial begin
    reset <= 1'b1;
    @(posedge clk);
    @(posedge clk);
    reset <= 1'b0;
   for (int i=0;i<128;i++)
      @(posedge clk);
    $finish();
  end

  initial begin
    $dumpfile("day5.vcd");
    $dumpvars(0, tb_od_counter);
  end
  
endmodule

Day5/day5.vcd
$date
   Sat May  4 07:35:17 2024
$end
$version
  2018.2
$end
$timescale
  1ps
$end
$scope module tb_od_counter $end
$var reg 1 ! clk $end
$var reg 1 " reset $end
$var reg 8 # od_counter [7:0] $end
$scope module day5 $end
$var wire 1 $ clk $end
$var wire 1 % reset $end
$var reg 8 # od_counter [7:0] $end
$var reg 8 & next_cnt [7:0] $end
$upscope $end
$upscope $end
$enddefinitions $end
#0
$dumpvars
0!
1"
b1 #
0$
1%
b11 &
$end
#5000
1!
1$
#10000
0!
0$
#15000
1!
0"
1$
0%
#20000
0!
0$
#25000
1!
b11 #
1$
b101 &
#30000
0!
0$
#35000
1!
b101 #
1$
b111 &
#40000
0!
0$
#45000
1!
b111 #
1$
b1001 &
#50000
0!
0$
#55000
1!
b1001 #
1$
b1011 &
#60000
0!
0$
#65000
1!
b1011 #
1$
b1101 &
#70000
0!
0$
#75000
1!
b1101 #
1$
b1111 &
#80000
0!
0$
#85000
1!
b1111 #
1$
b10001 &
#90000
0!
0$
#95000
1!
b10001 #
1$
b10011 &
#100000
0!
0$
#105000
1!
b10011 #
1$
b10101 &
#110000
0!
0$
#115000
1!
b10101 #
1$
b10111 &
#120000
0!
0$
#125000
1!
b10111 #
1$
b11001 &
#130000
0!
0$
#135000
1!
b11001 #
1$
b11011 &
#140000
0!
0$
#145000
1!
b11011 #
1$
b11101 &
#150000
0!
0$
#155000
1!
b11101 #
1$
b11111 &
#160000
0!
0$
#165000
1!
b11111 #
1$
b100001 &
#170000
0!
0$
#175000
1!
b100001 #
1$
b100011 &
#180000
0!
0$
#185000
1!
b100011 #
1$
b100101 &
#190000
0!
0$
#195000
1!
b100101 #
1$
b100111 &
#200000
0!
0$
#205000
1!
b100111 #
1$
b101001 &
#210000
0!
0$
#215000
1!
b101001 #
1$
b101011 &
#220000
0!
0$
#225000
1!
b101011 #
1$
b101101 &
#230000
0!
0$
#235000
1!
b101101 #
1$
b101111 &
#240000
0!
0$
#245000
1!
b101111 #
1$
b110001 &
#250000
0!
0$
#255000
1!
b110001 #
1$
b110011 &
#260000
0!
0$
#265000
1!
b110011 #
1$
b110101 &
#270000
0!
0$
#275000
1!
b110101 #
1$
b110111 &
#280000
0!
0$
#285000
1!
b110111 #
1$
b111001 &
#290000
0!
0$
#295000
1!
b111001 #
1$
b111011 &
#300000
0!
0$
#305000
1!
b111011 #
1$
b111101 &
#310000
0!
0$
#315000
1!
b111101 #
1$
b111111 &
#320000
0!
0$
#325000
1!
b111111 #
1$
b1000001 &
#330000
0!
0$
#335000
1!
b1000001 #
1$
b1000011 &
#340000
0!
0$
#345000
1!
b1000011 #
1$
b1000101 &
#350000
0!
0$
#355000
1!
b1000101 #
1$
b1000111 &
#360000
0!
0$
#365000
1!
b1000111 #
1$
b1001001 &
#370000
0!
0$
#375000
1!
b1001001 #
1$
b1001011 &
#380000
0!
0$
#385000
1!
b1001011 #
1$
b1001101 &
#390000
0!
0$
#395000
1!
b1001101 #
1$
b1001111 &
#400000
0!
0$
#405000
1!
b1001111 #
1$
b1010001 &
#410000
0!
0$
#415000
1!
b1010001 #
1$
b1010011 &
#420000
0!
0$
#425000
1!
b1010011 #
1$
b1010101 &
#430000
0!
0$
#435000
1!
b1010101 #
1$
b1010111 &
#440000
0!
0$
#445000
1!
b1010111 #
1$
b1011001 &
#450000
0!
0$
#455000
1!
b1011001 #
1$
b1011011 &
#460000
0!
0$
#465000
1!
b1011011 #
1$
b1011101 &
#470000
0!
0$
#475000
1!
b1011101 #
1$
b1011111 &
#480000
0!
0$
#485000
1!
b1011111 #
1$
b1100001 &
#490000
0!
0$
#495000
1!
b1100001 #
1$
b1100011 &
#500000
0!
0$
#505000
1!
b1100011 #
1$
b1100101 &
#510000
0!
0$
#515000
1!
b1100101 #
1$
b1100111 &
#520000
0!
0$
#525000
1!
b1100111 #
1$
b1101001 &
#530000
0!
0$
#535000
1!
b1101001 #
1$
b1101011 &
#540000
0!
0$
#545000
1!
b1101011 #
1$
b1101101 &
#550000
0!
0$
#555000
1!
b1101101 #
1$
b1101111 &
#560000
0!
0$
#565000
1!
b1101111 #
1$
b1110001 &
#570000
0!
0$
#575000
1!
b1110001 #
1$
b1110011 &
#580000
0!
0$
#585000
1!
b1110011 #
1$
b1110101 &
#590000
0!
0$
#595000
1!
b1110101 #
1$
b1110111 &
#600000
0!
0$
#605000
1!
b1110111 #
1$
b1111001 &
#610000
0!
0$
#615000
1!
b1111001 #
1$
b1111011 &
#620000
0!
0$
#625000
1!
b1111011 #
1$
b1111101 &
#630000
0!
0$
#635000
1!
b1111101 #
1$
b1111111 &
#640000
0!
0$
#645000
1!
b1111111 #
1$
b10000001 &
#650000
0!
0$
#655000
1!
b10000001 #
1$
b10000011 &
#660000
0!
0$
#665000
1!
b10000011 #
1$
b10000101 &
#670000
0!
0$
#675000
1!
b10000101 #
1$
b10000111 &
#680000
0!
0$
#685000
1!
b10000111 #
1$
b10001001 &
#690000
0!
0$
#695000
1!
b10001001 #
1$
b10001011 &
#700000
0!
0$
#705000
1!
b10001011 #
1$
b10001101 &
#710000
0!
0$
#715000
1!
b10001101 #
1$
b10001111 &
#720000
0!
0$
#725000
1!
b10001111 #
1$
b10010001 &
#730000
0!
0$
#735000
1!
b10010001 #
1$
b10010011 &
#740000
0!
0$
#745000
1!
b10010011 #
1$
b10010101 &
#750000
0!
0$
#755000
1!
b10010101 #
1$
b10010111 &
#760000
0!
0$
#765000
1!
b10010111 #
1$
b10011001 &
#770000
0!
0$
#775000
1!
b10011001 #
1$
b10011011 &
#780000
0!
0$
#785000
1!
b10011011 #
1$
b10011101 &
#790000
0!
0$
#795000
1!
b10011101 #
1$
b10011111 &
#800000
0!
0$
#805000
1!
b10011111 #
1$
b10100001 &
#810000
0!
0$
#815000
1!
b10100001 #
1$
b10100011 &
#820000
0!
0$
#825000
1!
b10100011 #
1$
b10100101 &
#830000
0!
0$
#835000
1!
b10100101 #
1$
b10100111 &
#840000
0!
0$
#845000
1!
b10100111 #
1$
b10101001 &
#850000
0!
0$
#855000
1!
b10101001 #
1$
b10101011 &
#860000
0!
0$
#865000
1!
b10101011 #
1$
b10101101 &
#870000
0!
0$
#875000
1!
b10101101 #
1$
b10101111 &
#880000
0!
0$
#885000
1!
b10101111 #
1$
b10110001 &
#890000
0!
0$
#895000
1!
b10110001 #
1$
b10110011 &
#900000
0!
0$
#905000
1!
b10110011 #
1$
b10110101 &
#910000
0!
0$
#915000
1!
b10110101 #
1$
b10110111 &
#920000
0!
0$
#925000
1!
b10110111 #
1$
b10111001 &
#930000
0!
0$
#935000
1!
b10111001 #
1$
b10111011 &
#940000
0!
0$
#945000
1!
b10111011 #
1$
b10111101 &
#950000
0!
0$
#955000
1!
b10111101 #
1$
b10111111 &
#960000
0!
0$
#965000
1!
b10111111 #
1$
b11000001 &
#970000
0!
0$
#975000
1!
b11000001 #
1$
b11000011 &
#980000
0!
0$
#985000
1!
b11000011 #
1$
b11000101 &
#990000
0!
0$
#995000
1!
b11000101 #
1$
b11000111 &
