Day8/binto_onehot.sv
`timescale 1ns / 1ps
//////////////////////////////////////////////////////////////////////////////////
// Company: 
// Engineer: 
// 
// Create Date: 05/04/2024 09:22:46 AM
// Design Name: 
// Module Name: binto_onehot
// Project Name: 
// Target Devices: 
// Tool Versions: 
// Description: 
// 
// Dependencies: 
// 
// Revision:
// Revision 0.01 - File Created
// Additional Comments:
// 
//////////////////////////////////////////////////////////////////////////////////


module binto_onehot #(
    parameter BIN_W = 4,
    parameter ONE_HOT_W = 16
)(
    input wire [BIN_W-1:0] bin_i,
    output wire [ONE_HOT_W-1:0] one_hot_o
    );
    
    assign one_hot_o = 1'b1<<bin_i;
    
endmodule

Day8/tb_binto_1hot.sv
`timescale 1ns / 1ps
//////////////////////////////////////////////////////////////////////////////////
// Company: 
// Engineer: 
// 
// Create Date: 05/04/2024 09:33:41 AM
// Design Name: 
// Module Name: tb_binto_1hot
// Project Name: 
// Target Devices: 
// Tool Versions: 
// Description: 
// 
// Dependencies: 
// 
// Revision:
// Revision 0.01 - File Created
// Additional Comments:
// 
//////////////////////////////////////////////////////////////////////////////////


    module tb_binto_1hot();
    
      localparam BIN_W = 4;
      localparam ONE_HOT_W = 16;
    
      logic [BIN_W-1:0] bin_i;
      logic [ONE_HOT_W-1:0] one_hot_o;
    
      binto_onehot #(BIN_W, ONE_HOT_W) DAY8 (.*);
    
      initial begin
        for(int i=0; i<32; i=i+1) begin
          bin_i = $urandom_range(0, 4'hF);
          #5;
        end
        $finish();
      end
    
      initial begin
        $dumpfile("day8.vcd");
        $dumpvars(2, tb_binto_1hot);
      end
    
    endmodule

Day8/day8.vcd
$date
   Sat May  4 09:49:19 2024
$end
$version
  2018.2
$end
$timescale
  1ps
$end
$scope module tb_binto_1hot $end
$var reg 4 ! bin_i [3:0] $end
$var reg 16 " one_hot_o [15:0] $end
$var parameter 32 # BIN_W [31:0] $end
$var parameter 32 $ ONE_HOT_W [31:0] $end
$scope module DAY8 $end
$var wire 4 % bin_i [3:0] $end
$var wire 16 & one_hot_o [15:0] $end
$var parameter 32 ' BIN_W [31:0] $end
$var parameter 32 ( ONE_HOT_W [31:0] $end
$upscope $end
$scope begin Block34_1 $end
$var reg 32 ) i $end
$upscope $end
$upscope $end
$enddefinitions $end
#0
$dumpvars
b11 !
b1000 "
b100 #
b10000 $
b11 %
b1000 &
b100 '
b10000 (
b0 )
$end
#5000
b1011 !
b100000000000 "
b1011 %
b100000000000 &
b1 )
#10000
b100 !
b10000 "
b100 %
b10000 &
b10 )
#15000
b110 !
b1000000 "
b110 %
b1000000 &
b11 )
#20000
b101 !
b100000 "
b101 %
b100000 &
b100 )
#25000
b1 !
b10 "
b1 %
b10 &
b101 )
#30000
b11 !
b1000 "
b11 %
b1000 &
b110 )
#35000
b1000 !
b100000000 "
b1000 %
b100000000 &
b111 )
#40000
b1101 !
b10000000000000 "
b1101 %
b10000000000000 &
b1000 )
#45000
b111 !
b10000000 "
b111 %
b10000000 &
b1001 )
#50000
b1111 !
b1000000000000000 "
b1111 %
b1000000000000000 &
b1010 )
#55000
b10 !
b100 "
b10 %
b100 &
b1011 )
#60000
b1000 !
b100000000 "
b1000 %
b100000000 &
b1100 )
#65000
b10 !
b100 "
b10 %
b100 &
b1101 )
#70000
b1010 !
b10000000000 "
b1010 %
b10000000000 &
b1110 )
#75000
b101 !
b100000 "
b101 %
b100000 &
b1111 )
#80000
b1001 !
b1000000000 "
b1001 %
b1000000000 &
b10000 )
#85000
b1001 !
b10001 )
#90000
b111 !
b10000000 "
b111 %
b10000000 &
b10010 )
#95000
b1 !
b10 "
b1 %
b10 &
b10011 )
#100000
b1011 !
b100000000000 "
b1011 %
b100000000000 &
b10100 )
#105000
b10 !
b100 "
b10 %
b100 &
b10101 )
#110000
b111 !
b10000000 "
b111 %
b10000000 &
b10110 )
#115000
b100 !
b10000 "
b100 %
b10000 &
b10111 )
#120000
b1011 !
b100000000000 "
b1011 %
b100000000000 &
b11000 )
#125000
b1110 !
b100000000000000 "
b1110 %
b100000000000000 &
b11001 )
#130000
b110 !
b1000000 "
b110 %
b1000000 &
b11010 )
#135000
b111 !
b10000000 "
b111 %
b10000000 &
b11011 )
#140000
b0 !
b1 "
b0 %
b1 &
b11100 )
#145000
b1101 !
b10000000000000 "
b1101 %
b10000000000000 &
b11101 )
#150000
b1011 !
b100000000000 "
b1011 %
b100000000000 &
b11110 )
#155000
b1100 !
b1000000000000 "
b1100 %
b1000000000000 &
b11111 )
